Workbook

Sheet README
A1: Caboodle — Jira Backlog Organized by Module
A3: Purpose | B3: 225 open tickets (Backlog / In Progress / In Staging / Ready for Production / Reopened) classified into the Caboodle module hierarchy to plan the 3-month sprint ahead of new-client onboarding.
A4: How it was built | B4: Each ticket was assigned an Area + Caboodle Module by reading its Summary (which references the module), with the original Jira "Module" column used as backup. The [FE]/[BE] tag was parsed from the summary into the FE/BE column for engineer allocation.
A6: TABS
A7: Module Summary | B7: Live count of tickets per module, broken out by status, priority, and FE vs BE. Formula-driven — edits to the Master tab flow through automatically.
A8: All Tickets (Master) | B8: Every ticket with its assigned Area, Module and FE/BE tag. This is the source of truth; the area tabs and summary read from it.
A9: Broker Dashboard / Brand / Reports / Admin / Platform | B9: One tab per Area, tickets grouped under their module heading and sorted by priority.
A11: NOTES & JUDGMENT CALLS
A12: Category Review | B12: Appears in two places: under Broker Dashboard (the broker-side review tool) and under Reports as "Category Review Report". Tickets tagged "Reports | Category Review" went to the report; the rest to Broker Dashboard.
A13: Trade Spend | B13: "Trade Spend Sandbox / TSS / EDLP / Everyday Allowance" → Brand module Trade Spend Sandbox. "Trade Spend Roll Up / Rollup Report" → Reports module Trade Spend Rollup.
A14: Platform & Cross-Cutting | B14: 30 tickets that do not belong to any single module — DB indexing, code refactor, caching, email service, QA/UX audits, big-data upload wizard, Ask Caboodle (AI), Tableau, margin calculator. Worth scoping separately from module work.
A15: Two new reports | B15: "Banner-to-DC Reporting" is flagged as a new report (not in the current 8-report list).
A16: Re-binning | B16: Because the Area & Module columns live on every row, you can re-sort or re-classify any ticket and the Module Summary updates instantly.

Sheet Module Summary
A1: Tickets by Caboodle Module
A3: Area | B3: Caboodle Module | C3: Total | D3: Backlog | E3: In Progress | F3: In Staging | G3: Ready for Prod | H3: Reopened | I3: Highest | J3: High | K3: Medium | L3: Low | M3: FE | N3: BE
A4: Broker Dashboard | B4: Market Overview | C4: =COUNTIFS('All Tickets (Master)'!$D$2:$D$227,$A4,'All Tickets (Master)'!$E$2:$E$227,$B4) -> 6 | D4: =COUNTIFS('All Tickets (Master)'!$D$2:$D$227,$A4,'All Tickets (Master)'!$E$2:$E$227,$B4,'All Tickets (Master)'!$H$2:$H$227,"Backlog") -> 5 | E4: =COUNTIFS('All Tickets (Master)'!$D$2:$D$227,$A4,'All Tickets (Master)'!$E$2:$E$227,$B4,'All Tickets (Master)'!$H$2:$H$227,"In Progress") -> 1 | F4: =COUNTIFS('All Tickets (Master)'!$D$2:$D$227,$A4,'All Tickets (Master)'!$E$2:$E$227,$B4,'All Tickets (Master)'!$H$2:$H$227,"In Staging") -> 0 | G4: =COUNTIFS('All Tickets (Master)'!$D$2:$D$227,$A4,'All Tickets (Master)'!$E$2:$E$227,$B4,'All Tickets (Master)'!$H$2:$H$227,"Ready for Production") -> 0 | H4: =COUNTIFS('All Tickets (Master)'!$D$2:$D$227,$A4,'All Tickets (Master)'!$E$2:$E$227,$B4,'All Tickets (Master)'!$H$2:$H$227,"Reopened") -> 0 | I4: =COUNTIFS('All Tickets (Master)'!$D$2:$D$227,$A4,'All Tickets (Master)'!$E$2:$E$227,$B4,'All Tickets (Master)'!$G$2:$G$227,"Highest") -> 0 | J4: =COUNTIFS('All Tickets (Master)'!$D$2:$D$227,$A4,'All Tickets (Master)'!$E$2:$E$227,$B4,'All Tickets (Master)'!$G$2:$G$227,"High") -> 6 | K4: =COUNTIFS('All Tickets (Master)'!$D$2:$D$227,$A4,'All Tickets (Master)'!$E$2:$E$227,$B4,'All Tickets (Master)'!$G$2:$G$227,"Medium") -> 0 | L4: =COUNTIFS('All Tickets (Master)'!$D$2:$D$227,$A4,'All Tickets (Master)'!$E$2:$E$227,$B4,'All Tickets (Master)'!$G$2:$G$227,"Low") -> 0 | M4: =COUNTIFS('All Tickets (Master)'!$D$2:$D$227,$A4,'All Tickets (Master)'!$E$2:$E$227,$B4,'All Tickets (Master)'!$F$2:$F$227,"FE") -> 0 | N4: =COUNTIFS('All Tickets (Master)'!$D$2:$D$227,$A4,'All Tickets (Master)'!$E$2:$E$227,$B4,'All Tickets (Master)'!$F$2:$F$227,"BE") -> 1
A5: Broker Dashboard | B5: Promotional Management | C5: =COUNTIFS('All Tickets (Master)'!$D$2:$D$227,$A5,'All Tickets (Master)'!$E$2:$E$227,$B5) -> 5 | D5: =COUNTIFS('All Tickets (Master)'!$D$2:$D$227,$A5,'All Tickets (Master)'!$E$2:$E$227,$B5,'All Tickets (Master)'!$H$2:$H$227,"Backlog") -> 5 | E5: =COUNTIFS('All Tickets (Master)'!$D$2:$D$227,$A5,'All Tickets (Master)'!$E$2:$E$227,$B5,'All Tickets (Master)'!$H$2:$H$227,"In Progress") -> 0 | F5: =COUNTIFS('All Tickets (Master)'!$D$2:$D$227,$A5,'All Tickets (Master)'!$E$2:$E$227,$B5,'All Tickets (Master)'!$H$2:$H$227,"In Staging") -> 0 | G5: =COUNTIFS('All Tickets (Master)'!$D$2:$D$227,$A5,'All Tickets (Master)'!$E$2:$E$227,$B5,'All Tickets (Master)'!$H$2:$H$227,"Ready for Production") -> 0 | H5: =COUNTIFS('All Tickets (Master)'!$D$2:$D$227,$A5,'All Tickets (Master)'!$E$2:$E$227,$B5,'All Tickets (Master)'!$H$2:$H$227,"Reopened") -> 0 | I5: =COUNTIFS('All Tickets (Master)'!$D$2:$D$227,$A5,'All Tickets (Master)'!$E$2:$E$227,$B5,'All Tickets (Master)'!$G$2:$G$227,"Highest") -> 0 | J5: =COUNTIFS('All Tickets (Master)'!$D$2:$D$227,$A5,'All Tickets (Master)'!$E$2:$E$227,$B5,'All Tickets (Master)'!$G$2:$G$227,"High") -> 3 | K5: =COUNTIFS('All Tickets (Master)'!$D$2:$D$227,$A5,'All Tickets (Master)'!$E$2:$E$227,$B5,'All Tickets (Master)'!$G$2:$G$227,"Medium") -> 1 | L5: =COUNTIFS('All Tickets (Master)'!$D$2:$D$227,$A5,'All Tickets (Master)'!$E$2:$E$227,$B5,'All Tickets (Master)'!$G$2:$G$227,"Low") -> 1 | M5: =COUNTIFS('All Tickets (Master)'!$D$2:$D$227,$A5,'All Tickets (Master)'!$E$2:$E$227,$B5,'All Tickets (Master)'!$F$2:$F$227,"FE") -> 0 | N5: =COUNTIFS('All Tickets (Master)'!$D$2:$D$227,$A5,'All Tickets (Master)'!$E$2:$E$227,$B5,'All Tickets (Master)'!$F$2:$F$227,"BE") -> 2
A6: Broker Dashboard | B6: Category Review | C6: =COUNTIFS('All Tickets (Master)'!$D$2:$D$227,$A6,'All Tickets (Master)'!$E$2:$E$227,$B6) -> 11 | D6: =COUNTIFS('All Tickets (Master)'!$D$2:$D$227,$A6,'All Tickets (Master)'!$E$2:$E$227,$B6,'All Tickets (Master)'!$H$2:$H$227,"Backlog") -> 9 | E6: =COUNTIFS('All Tickets (Master)'!$D$2:$D$227,$A6,'All Tickets (Master)'!$E$2:$E$227,$B6,'All Tickets (Master)'!$H$2:$H$227,"In Progress") -> 1 | F6: =COUNTIFS('All Tickets (Master)'!$D$2:$D$227,$A6,'All Tickets (Master)'!$E$2:$E$227,$B6,'All Tickets (Master)'!$H$2:$H$227,"In Staging") -> 0 | G6: =COUNTIFS('All Tickets (Master)'!$D$2:$D$227,$A6,'All Tickets (Master)'!$E$2:$E$227,$B6,'All Tickets (Master)'!$H$2:$H$227,"Ready for Production") -> 0 | H6: =COUNTIFS('All Tickets (Master)'!$D$2:$D$227,$A6,'All Tickets (Master)'!$E$2:$E$227,$B6,'All Tickets (Master)'!$H$2:$H$227,"Reopened") -> 1 | I6: =COUNTIFS('All Tickets (Master)'!$D$2:$D$227,$A6,'All Tickets (Master)'!$E$2:$E$227,$B6,'All Tickets (Master)'!$G$2:$G$227,"Highest") -> 1 | J6: =COUNTIFS('All Tickets (Master)'!$D$2:$D$227,$A6,'All Tickets (Master)'!$E$2:$E$227,$B6,'All Tickets (Master)'!$G$2:$G$227,"High") -> 10 | K6: =COUNTIFS('All Tickets (Master)'!$D$2:$D$227,$A6,'All Tickets (Master)'!$E$2:$E$227,$B6,'All Tickets (Master)'!$G$2:$G$227,"Medium") -> 0 | L6: =COUNTIFS('All Tickets (Master)'!$D$2:$D$227,$A6,'All Tickets (Master)'!$E$2:$E$227,$B6,'All Tickets (Master)'!$G$2:$G$227,"Low") -> 0 | M6: =COUNTIFS('All Tickets (Master)'!$D$2:$D$227,$A6,'All Tickets (Master)'!$E$2:$E$227,$B6,'All Tickets (Master)'!$F$2:$F$227,"FE") -> 0 | N6: =COUNTIFS('All Tickets (Master)'!$D$2:$D$227,$A6,'All Tickets (Master)'!$E$2:$E$227,$B6,'All Tickets (Master)'!$F$2:$F$227,"BE") -> 0
A7: Broker Dashboard | B7: Distributor APL | C7: =COUNTIFS('All Tickets (Master)'!$D$2:$D$227,$A7,'All Tickets (Master)'!$E$2:$E$227,$B7) -> 4 | D7: =COUNTIFS('All Tickets (Master)'!$D$2:$D$227,$A7,'All Tickets (Master)'!$E$2:$E$227,$B7,'All Tickets (Master)'!$H$2:$H$227,"Backlog") -> 4 | E7: =COUNTIFS('All Tickets (Master)'!$D$2:$D$227,$A7,'All Tickets (Master)'!$E$2:$E$227,$B7,'All Tickets (Master)'!$H$2:$H$227,"In Progress") -> 0 | F7: =COUNTIFS('All Tickets (Master)'!$D$2:$D$227,$A7,'All Tickets (Master)'!$E$2:$E$227,$B7,'All Tickets (Master)'!$H$2:$H$227,"In Staging") -> 0 | G7: =COUNTIFS('All Tickets (Master)'!$D$2:$D$227,$A7,'All Tickets (Master)'!$E$2:$E$227,$B7,'All Tickets (Master)'!$H$2:$H$227,"Ready for Production") -> 0 | H7: =COUNTIFS('All Tickets (Master)'!$D$2:$D$227,$A7,'All Tickets (Master)'!$E$2:$E$227,$B7,'All Tickets (Master)'!$H$2:$H$227,"Reopened") -> 0 | I7: =COUNTIFS('All Tickets (Master)'!$D$2:$D$227,$A7,'All Tickets (Master)'!$E$2:$E$227,$B7,'All Tickets (Master)'!$G$2:$G$227,"Highest") -> 1 | J7: =COUNTIFS('All Tickets (Master)'!$D$2:$D$227,$A7,'All Tickets (Master)'!$E$2:$E$227,$B7,'All Tickets (Master)'!$G$2:$G$227,"High") -> 3 | K7: =COUNTIFS('All Tickets (Master)'!$D$2:$D$227,$A7,'All Tickets (Master)'!$E$2:$E$227,$B7,'All Tickets (Master)'!$G$2:$G$227,"Medium") -> 0 | L7: =COUNTIFS('All Tickets (Master)'!$D$2:$D$227,$A7,'All Tickets (Master)'!$E$2:$E$227,$B7,'All Tickets (Master)'!$G$2:$G$227,"Low") -> 0 | M7: =COUNTIFS('All Tickets (Master)'!$D$2:$D$227,$A7,'All Tickets (Master)'!$E$2:$E$227,$B7,'All Tickets (Master)'!$F$2:$F$227,"FE") -> 0 | N7: =COUNTIFS('All Tickets (Master)'!$D$2:$D$227,$A7,'All Tickets (Master)'!$E$2:$E$227,$B7,'All Tickets (Master)'!$F$2:$F$227,"BE") -> 0
A8: Broker Dashboard | B8: Files | C8: =COUNTIFS('All Tickets (Master)'!$D$2:$D$227,$A8,'All Tickets (Master)'!$E$2:$E$227,$B8) -> 3 | D8: =COUNTIFS('All Tickets (Master)'!$D$2:$D$227,$A8,'All Tickets (Master)'!$E$2:$E$227,$B8,'All Tickets (Master)'!$H$2:$H$227,"Backlog") -> 3 | E8: =COUNTIFS('All Tickets (Master)'!$D$2:$D$227,$A8,'All Tickets (Master)'!$E$2:$E$227,$B8,'All Tickets (Master)'!$H$2:$H$227,"In Progress") -> 0 | F8: =COUNTIFS('All Tickets (Master)'!$D$2:$D$227,$A8,'All Tickets (Master)'!$E$2:$E$227,$B8,'All Tickets (Master)'!$H$2:$H$227,"In Staging") -> 0 | G8: =COUNTIFS('All Tickets (Master)'!$D$2:$D$227,$A8,'All Tickets (Master)'!$E$2:$E$227,$B8,'All Tickets (Master)'!$H$2:$H$227,"Ready for Production") -> 0 | H8: =COUNTIFS('All Tickets (Master)'!$D$2:$D$227,$A8,'All Tickets (Master)'!$E$2:$E$227,$B8,'All Tickets (Master)'!$H$2:$H$227,"Reopened") -> 0 | I8: =COUNTIFS('All Tickets (Master)'!$D$2:$D$227,$A8,'All Tickets (Master)'!$E$2:$E$227,$B8,'All Tickets (Master)'!$G$2:$G$227,"Highest") -> 2 | J8: =COUNTIFS('All Tickets (Master)'!$D$2:$D$227,$A8,'All Tickets (Master)'!$E$2:$E$227,$B8,'All Tickets (Master)'!$G$2:$G$227,"High") -> 1 | K8: =COUNTIFS('All Tickets (Master)'!$D$2:$D$227,$A8,'All Tickets (Master)'!$E$2:$E$227,$B8,'All Tickets (Master)'!$G$2:$G$227,"Medium") -> 0 | L8: =COUNTIFS('All Tickets (Master)'!$D$2:$D$227,$A8,'All Tickets (Master)'!$E$2:$E$227,$B8,'All Tickets (Master)'!$G$2:$G$227,"Low") -> 0 | M8: =COUNTIFS('All Tickets (Master)'!$D$2:$D$227,$A8,'All Tickets (Master)'!$E$2:$E$227,$B8,'All Tickets (Master)'!$F$2:$F$227,"FE") -> 0 | N8: =COUNTIFS('All Tickets (Master)'!$D$2:$D$227,$A8,'All Tickets (Master)'!$E$2:$E$227,$B8,'All Tickets (Master)'!$F$2:$F$227,"BE") -> 0
A9: Broker Dashboard | B9: Broker Dashboard (General) | C9: =COUNTIFS('All Tickets (Master)'!$D$2:$D$227,$A9,'All Tickets (Master)'!$E$2:$E$227,$B9) -> 4 | D9: =COUNTIFS('All Tickets (Master)'!$D$2:$D$227,$A9,'All Tickets (Master)'!$E$2:$E$227,$B9,'All Tickets (Master)'!$H$2:$H$227,"Backlog") -> 4 | E9: =COUNTIFS('All Tickets (Master)'!$D$2:$D$227,$A9,'All Tickets (Master)'!$E$2:$E$227,$B9,'All Tickets (Master)'!$H$2:$H$227,"In Progress") -> 0 | F9: =COUNTIFS('All Tickets (Master)'!$D$2:$D$227,$A9,'All Tickets (Master)'!$E$2:$E$227,$B9,'All Tickets (Master)'!$H$2:$H$227,"In Staging") -> 0 | G9: =COUNTIFS('All Tickets (Master)'!$D$2:$D$227,$A9,'All Tickets (Master)'!$E$2:$E$227,$B9,'All Tickets (Master)'!$H$2:$H$227,"Ready for Production") -> 0 | H9: =COUNTIFS('All Tickets (Master)'!$D$2:$D$227,$A9,'All Tickets (Master)'!$E$2:$E$227,$B9,'All Tickets (Master)'!$H$2:$H$227,"Reopened") -> 0 | I9: =COUNTIFS('All Tickets (Master)'!$D$2:$D$227,$A9,'All Tickets (Master)'!$E$2:$E$227,$B9,'All Tickets (Master)'!$G$2:$G$227,"Highest") -> 0 | J9: =COUNTIFS('All Tickets (Master)'!$D$2:$D$227,$A9,'All Tickets (Master)'!$E$2:$E$227,$B9,'All Tickets (Master)'!$G$2:$G$227,"High") -> 3 | K9: =COUNTIFS('All Tickets (Master)'!$D$2:$D$227,$A9,'All Tickets (Master)'!$E$2:$E$227,$B9,'All Tickets (Master)'!$G$2:$G$227,"Medium") -> 0 | L9: =COUNTIFS('All Tickets (Master)'!$D$2:$D$227,$A9,'All Tickets (Master)'!$E$2:$E$227,$B9,'All Tickets (Master)'!$G$2:$G$227,"Low") -> 1 | M9: =COUNTIFS('All Tickets (Master)'!$D$2:$D$227,$A9,'All Tickets (Master)'!$E$2:$E$227,$B9,'All Tickets (Master)'!$F$2:$F$227,"FE") -> 0 | N9: =COUNTIFS('All Tickets (Master)'!$D$2:$D$227,$A9,'All Tickets (Master)'!$E$2:$E$227,$B9,'All Tickets (Master)'!$F$2:$F$227,"BE") -> 1
A10: Brand | B10: Product Specs | C10: =COUNTIFS('All Tickets (Master)'!$D$2:$D$227,$A10,'All Tickets (Master)'!$E$2:$E$227,$B10) -> 8 | D10: =COUNTIFS('All Tickets (Master)'!$D$2:$D$227,$A10,'All Tickets (Master)'!$E$2:$E$227,$B10,'All Tickets (Master)'!$H$2:$H$227,"Backlog") -> 5 | E10: =COUNTIFS('All Tickets (Master)'!$D$2:$D$227,$A10,'All Tickets (Master)'!$E$2:$E$227,$B10,'All Tickets (Master)'!$H$2:$H$227,"In Progress") -> 1 | F10: =COUNTIFS('All Tickets (Master)'!$D$2:$D$227,$A10,'All Tickets (Master)'!$E$2:$E$227,$B10,'All Tickets (Master)'!$H$2:$H$227,"In Staging") -> 0 | G10: =COUNTIFS('All Tickets (Master)'!$D$2:$D$227,$A10,'All Tickets (Master)'!$E$2:$E$227,$B10,'All Tickets (Master)'!$H$2:$H$227,"Ready for Production") -> 0 | H10: =COUNTIFS('All Tickets (Master)'!$D$2:$D$227,$A10,'All Tickets (Master)'!$E$2:$E$227,$B10,'All Tickets (Master)'!$H$2:$H$227,"Reopened") -> 2 | I10: =COUNTIFS('All Tickets (Master)'!$D$2:$D$227,$A10,'All Tickets (Master)'!$E$2:$E$227,$B10,'All Tickets (Master)'!$G$2:$G$227,"Highest") -> 1 | J10: =COUNTIFS('All Tickets (Master)'!$D$2:$D$227,$A10,'All Tickets (Master)'!$E$2:$E$227,$B10,'All Tickets (Master)'!$G$2:$G$227,"High") -> 4 | K10: =COUNTIFS('All Tickets (Master)'!$D$2:$D$227,$A10,'All Tickets (Master)'!$E$2:$E$227,$B10,'All Tickets (Master)'!$G$2:$G$227,"Medium") -> 2 | L10: =COUNTIFS('All Tickets (Master)'!$D$2:$D$227,$A10,'All Tickets (Master)'!$E$2:$E$227,$B10,'All Tickets (Master)'!$G$2:$G$227,"Low") -> 1 | M10: =COUNTIFS('All Tickets (Master)'!$D$2:$D$227,$A10,'All Tickets (Master)'!$E$2:$E$227,$B10,'All Tickets (Master)'!$F$2:$F$227,"FE") -> 0 | N10: =COUNTIFS('All Tickets (Master)'!$D$2:$D$227,$A10,'All Tickets (Master)'!$E$2:$E$227,$B10,'All Tickets (Master)'!$F$2:$F$227,"BE") -> 2
A11: Brand | B11: Distributors | C11: =COUNTIFS('All Tickets (Master)'!$D$2:$D$227,$A11,'All Tickets (Master)'!$E$2:$E$227,$B11) -> 1 | D11: =COUNTIFS('All Tickets (Master)'!$D$2:$D$227,$A11,'All Tickets (Master)'!$E$2:$E$227,$B11,'All Tickets (Master)'!$H$2:$H$227,"Backlog") -> 0 | E11: =COUNTIFS('All Tickets (Master)'!$D$2:$D$227,$A11,'All Tickets (Master)'!$E$2:$E$227,$B11,'All Tickets (Master)'!$H$2:$H$227,"In Progress") -> 1 | F11: =COUNTIFS('All Tickets (Master)'!$D$2:$D$227,$A11,'All Tickets (Master)'!$E$2:$E$227,$B11,'All Tickets (Master)'!$H$2:$H$227,"In Staging") -> 0 | G11: =COUNTIFS('All Tickets (Master)'!$D$2:$D$227,$A11,'All Tickets (Master)'!$E$2:$E$227,$B11,'All Tickets (Master)'!$H$2:$H$227,"Ready for Production") -> 0 | H11: =COUNTIFS('All Tickets (Master)'!$D$2:$D$227,$A11,'All Tickets (Master)'!$E$2:$E$227,$B11,'All Tickets (Master)'!$H$2:$H$227,"Reopened") -> 0 | I11: =COUNTIFS('All Tickets (Master)'!$D$2:$D$227,$A11,'All Tickets (Master)'!$E$2:$E$227,$B11,'All Tickets (Master)'!$G$2:$G$227,"Highest") -> 1 | J11: =COUNTIFS('All Tickets (Master)'!$D$2:$D$227,$A11,'All Tickets (Master)'!$E$2:$E$227,$B11,'All Tickets (Master)'!$G$2:$G$227,"High") -> 0 | K11: =COUNTIFS('All Tickets (Master)'!$D$2:$D$227,$A11,'All Tickets (Master)'!$E$2:$E$227,$B11,'All Tickets (Master)'!$G$2:$G$227,"Medium") -> 0 | L11: =COUNTIFS('All Tickets (Master)'!$D$2:$D$227,$A11,'All Tickets (Master)'!$E$2:$E$227,$B11,'All Tickets (Master)'!$G$2:$G$227,"Low") -> 0 | M11: =COUNTIFS('All Tickets (Master)'!$D$2:$D$227,$A11,'All Tickets (Master)'!$E$2:$E$227,$B11,'All Tickets (Master)'!$F$2:$F$227,"FE") -> 0 | N11: =COUNTIFS('All Tickets (Master)'!$D$2:$D$227,$A11,'All Tickets (Master)'!$E$2:$E$227,$B11,'All Tickets (Master)'!$F$2:$F$227,"BE") -> 0
A12: Brand | B12: Retailers | C12: =COUNTIFS('All Tickets (Master)'!$D$2:$D$227,$A12,'All Tickets (Master)'!$E$2:$E$227,$B12) -> 3 | D12: =COUNTIFS('All Tickets (Master)'!$D$2:$D$227,$A12,'All Tickets (Master)'!$E$2:$E$227,$B12,'All Tickets (Master)'!$H$2:$H$227,"Backlog") -> 1 | E12: =COUNTIFS('All Tickets (Master)'!$D$2:$D$227,$A12,'All Tickets (Master)'!$E$2:$E$227,$B12,'All Tickets (Master)'!$H$2:$H$227,"In Progress") -> 1 | F12: =COUNTIFS('All Tickets (Master)'!$D$2:$D$227,$A12,'All Tickets (Master)'!$E$2:$E$227,$B12,'All Tickets (Master)'!$H$2:$H$227,"In Staging") -> 1 | G12: =COUNTIFS('All Tickets (Master)'!$D$2:$D$227,$A12,'All Tickets (Master)'!$E$2:$E$227,$B12,'All Tickets (Master)'!$H$2:$H$227,"Ready for Production") -> 0 | H12: =COUNTIFS('All Tickets (Master)'!$D$2:$D$227,$A12,'All Tickets (Master)'!$E$2:$E$227,$B12,'All Tickets (Master)'!$H$2:$H$227,"Reopened") -> 0 | I12: =COUNTIFS('All Tickets (Master)'!$D$2:$D$227,$A12,'All Tickets (Master)'!$E$2:$E$227,$B12,'All Tickets (Master)'!$G$2:$G$227,"Highest") -> 1 | J12: =COUNTIFS('All Tickets (Master)'!$D$2:$D$227,$A12,'All Tickets (Master)'!$E$2:$E$227,$B12,'All Tickets (Master)'!$G$2:$G$227,"High") -> 0 | K12: =COUNTIFS('All Tickets (Master)'!$D$2:$D$227,$A12,'All Tickets (Master)'!$E$2:$E$227,$B12,'All Tickets (Master)'!$G$2:$G$227,"Medium") -> 1 | L12: =COUNTIFS('All Tickets (Master)'!$D$2:$D$227,$A12,'All Tickets (Master)'!$E$2:$E$227,$B12,'All Tickets (Master)'!$G$2:$G$227,"Low") -> 1 | M12: =COUNTIFS('All Tickets (Master)'!$D$2:$D$227,$A12,'All Tickets (Master)'!$E$2:$E$227,$B12,'All Tickets (Master)'!$F$2:$F$227,"FE") -> 0 | N12: =COUNTIFS('All Tickets (Master)'!$D$2:$D$227,$A12,'All Tickets (Master)'!$E$2:$E$227,$B12,'All Tickets (Master)'!$F$2:$F$227,"BE") -> 2
A13: Brand | B13: Contacts | C13: =COUNTIFS('All Tickets (Master)'!$D$2:$D$227,$A13,'All Tickets (Master)'!$E$2:$E$227,$B13) -> 1 | D13: =COUNTIFS('All Tickets (Master)'!$D$2:$D$227,$A13,'All Tickets (Master)'!$E$2:$E$227,$B13,'All Tickets (Master)'!$H$2:$H$227,"Backlog") -> 1 | E13: =COUNTIFS('All Tickets (Master)'!$D$2:$D$227,$A13,'All Tickets (Master)'!$E$2:$E$227,$B13,'All Tickets (Master)'!$H$2:$H$227,"In Progress") -> 0 | F13: =COUNTIFS('All Tickets (Master)'!$D$2:$D$227,$A13,'All Tickets (Master)'!$E$2:$E$227,$B13,'All Tickets (Master)'!$H$2:$H$227,"In Staging") -> 0 | G13: =COUNTIFS('All Tickets (Master)'!$D$2:$D$227,$A13,'All Tickets (Master)'!$E$2:$E$227,$B13,'All Tickets (Master)'!$H$2:$H$227,"Ready for Production") -> 0 | H13: =COUNTIFS('All Tickets (Master)'!$D$2:$D$227,$A13,'All Tickets (Master)'!$E$2:$E$227,$B13,'All Tickets (Master)'!$H$2:$H$227,"Reopened") -> 0 | I13: =COUNTIFS('All Tickets (Master)'!$D$2:$D$227,$A13,'All Tickets (Master)'!$E$2:$E$227,$B13,'All Tickets (Master)'!$G$2:$G$227,"Highest") -> 0 | J13: =COUNTIFS('All Tickets (Master)'!$D$2:$D$227,$A13,'All Tickets (Master)'!$E$2:$E$227,$B13,'All Tickets (Master)'!$G$2:$G$227,"High") -> 0 | K13: =COUNTIFS('All Tickets (Master)'!$D$2:$D$227,$A13,'All Tickets (Master)'!$E$2:$E$227,$B13,'All Tickets (Master)'!$G$2:$G$227,"Medium") -> 1 | L13: =COUNTIFS('All Tickets (Master)'!$D$2:$D$227,$A13,'All Tickets (Master)'!$E$2:$E$227,$B13,'All Tickets (Master)'!$G$2:$G$227,"Low") -> 0 | M13: =COUNTIFS('All Tickets (Master)'!$D$2:$D$227,$A13,'All Tickets (Master)'!$E$2:$E$227,$B13,'All Tickets (Master)'!$F$2:$F$227,"FE") -> 0 | N13: =COUNTIFS('All Tickets (Master)'!$D$2:$D$227,$A13,'All Tickets (Master)'!$E$2:$E$227,$B13,'All Tickets (Master)'!$F$2:$F$227,"BE") -> 0
A14: Brand | B14: Pipeline | C14: =COUNTIFS('All Tickets (Master)'!$D$2:$D$227,$A14,'All Tickets (Master)'!$E$2:$E$227,$B14) -> 5 | D14: =COUNTIFS('All Tickets (Master)'!$D$2:$D$227,$A14,'All Tickets (Master)'!$E$2:$E$227,$B14,'All Tickets (Master)'!$H$2:$H$227,"Backlog") -> 5 | E14: =COUNTIFS('All Tickets (Master)'!$D$2:$D$227,$A14,'All Tickets (Master)'!$E$2:$E$227,$B14,'All Tickets (Master)'!$H$2:$H$227,"In Progress") -> 0 | F14: =COUNTIFS('All Tickets (Master)'!$D$2:$D$227,$A14,'All Tickets (Master)'!$E$2:$E$227,$B14,'All Tickets (Master)'!$H$2:$H$227,"In Staging") -> 0 | G14: =COUNTIFS('All Tickets (Master)'!$D$2:$D$227,$A14,'All Tickets (Master)'!$E$2:$E$227,$B14,'All Tickets (Master)'!$H$2:$H$227,"Ready for Production") -> 0 | H14: =COUNTIFS('All Tickets (Master)'!$D$2:$D$227,$A14,'All Tickets (Master)'!$E$2:$E$227,$B14,'All Tickets (Master)'!$H$2:$H$227,"Reopened") -> 0 | I14: =COUNTIFS('All Tickets (Master)'!$D$2:$D$227,$A14,'All Tickets (Master)'!$E$2:$E$227,$B14,'All Tickets (Master)'!$G$2:$G$227,"Highest") -> 0 | J14: =COUNTIFS('All Tickets (Master)'!$D$2:$D$227,$A14,'All Tickets (Master)'!$E$2:$E$227,$B14,'All Tickets (Master)'!$G$2:$G$227,"High") -> 3 | K14: =COUNTIFS('All Tickets (Master)'!$D$2:$D$227,$A14,'All Tickets (Master)'!$E$2:$E$227,$B14,'All Tickets (Master)'!$G$2:$G$227,"Medium") -> 1 | L14: =COUNTIFS('All Tickets (Master)'!$D$2:$D$227,$A14,'All Tickets (Master)'!$E$2:$E$227,$B14,'All Tickets (Master)'!$G$2:$G$227,"Low") -> 1 | M14: =COUNTIFS('All Tickets (Master)'!$D$2:$D$227,$A14,'All Tickets (Master)'!$E$2:$E$227,$B14,'All Tickets (Master)'!$F$2:$F$227,"FE") -> 0 | N14: =COUNTIFS('All Tickets (Master)'!$D$2:$D$227,$A14,'All Tickets (Master)'!$E$2:$E$227,$B14,'All Tickets (Master)'!$F$2:$F$227,"BE") -> 0
A15: Brand | B15: Trade Spend Sandbox | C15: =COUNTIFS('All Tickets (Master)'!$D$2:$D$227,$A15,'All Tickets (Master)'!$E$2:$E$227,$B15) -> 37 | D15: =COUNTIFS('All Tickets (Master)'!$D$2:$D$227,$A15,'All Tickets (Master)'!$E$2:$E$227,$B15,'All Tickets (Master)'!$H$2:$H$227,"Backlog") -> 28 | E15: =COUNTIFS('All Tickets (Master)'!$D$2:$D$227,$A15,'All Tickets (Master)'!$E$2:$E$227,$B15,'All Tickets (Master)'!$H$2:$H$227,"In Progress") -> 1 | F15: =COUNTIFS('All Tickets (Master)'!$D$2:$D$227,$A15,'All Tickets (Master)'!$E$2:$E$227,$B15,'All Tickets (Master)'!$H$2:$H$227,"In Staging") -> 3 | G15: =COUNTIFS('All Tickets (Master)'!$D$2:$D$227,$A15,'All Tickets (Master)'!$E$2:$E$227,$B15,'All Tickets (Master)'!$H$2:$H$227,"Ready for Production") -> 4 | H15: =COUNTIFS('All Tickets (Master)'!$D$2:$D$227,$A15,'All Tickets (Master)'!$E$2:$E$227,$B15,'All Tickets (Master)'!$H$2:$H$227,"Reopened") -> 1 | I15: =COUNTIFS('All Tickets (Master)'!$D$2:$D$227,$A15,'All Tickets (Master)'!$E$2:$E$227,$B15,'All Tickets (Master)'!$G$2:$G$227,"Highest") -> 5 | J15: =COUNTIFS('All Tickets (Master)'!$D$2:$D$227,$A15,'All Tickets (Master)'!$E$2:$E$227,$B15,'All Tickets (Master)'!$G$2:$G$227,"High") -> 21 | K15: =COUNTIFS('All Tickets (Master)'!$D$2:$D$227,$A15,'All Tickets (Master)'!$E$2:$E$227,$B15,'All Tickets (Master)'!$G$2:$G$227,"Medium") -> 5 | L15: =COUNTIFS('All Tickets (Master)'!$D$2:$D$227,$A15,'All Tickets (Master)'!$E$2:$E$227,$B15,'All Tickets (Master)'!$G$2:$G$227,"Low") -> 6 | M15: =COUNTIFS('All Tickets (Master)'!$D$2:$D$227,$A15,'All Tickets (Master)'!$E$2:$E$227,$B15,'All Tickets (Master)'!$F$2:$F$227,"FE") -> 2 | N15: =COUNTIFS('All Tickets (Master)'!$D$2:$D$227,$A15,'All Tickets (Master)'!$E$2:$E$227,$B15,'All Tickets (Master)'!$F$2:$F$227,"BE") -> 1
... A31: Platform & Cross-Cutting | B31: Infrastructure / Cross-Cutting | C31: =COUNTIFS('All Tickets (Master)'!$D$2:$D$227,$A31,'All Tickets (Master)'!$E$2:$E$227,$B31) -> 28 | D31: =COUNTIFS('All Tickets (Master)'!$D$2:$D$227,$A31,'All Tickets (Master)'!$E$2:$E$227,$B31,'All Tickets (Master)'!$H$2:$H$227,"Backlog") -> 22 | E31: =COUNTIFS('All Tickets (Master)'!$D$2:$D$227,$A31,'All Tickets (Master)'!$E$2:$E$227,$B31,'All Tickets (Master)'!$H$2:$H$227,"In Progress") -> 4 | F31: =COUNTIFS('All Tickets (Master)'!$D$2:$D$227,$A31,'All Tickets (Master)'!$E$2:$E$227,$B31,'All Tickets (Master)'!$H$2:$H$227,"In Staging") -> 0 | G31: =COUNTIFS('All Tickets (Master)'!$D$2:$D$227,$A31,'All Tickets (Master)'!$E$2:$E$227,$B31,'All Tickets (Master)'!$H$2:$H$227,"Ready for Production") -> 1 | H31: =COUNTIFS('All Tickets (Master)'!$D$2:$D$227,$A31,'All Tickets (Master)'!$E$2:$E$227,$B31,'All Tickets (Master)'!$H$2:$H$227,"Reopened") -> 1 | I31: =COUNTIFS('All Tickets (Master)'!$D$2:$D$227,$A31,'All Tickets (Master)'!$E$2:$E$227,$B31,'All Tickets (Master)'!$G$2:$G$227,"Highest") -> 2 | J31: =COUNTIFS('All Tickets (Master)'!$D$2:$D$227,$A31,'All Tickets (Master)'!$E$2:$E$227,$B31,'All Tickets (Master)'!$G$2:$G$227,"High") -> 14 | K31: =COUNTIFS('All Tickets (Master)'!$D$2:$D$227,$A31,'All Tickets (Master)'!$E$2:$E$227,$B31,'All Tickets (Master)'!$G$2:$G$227,"Medium") -> 6 | L31: =COUNTIFS('All Tickets (Master)'!$D$2:$D$227,$A31,'All Tickets (Master)'!$E$2:$E$227,$B31,'All Tickets (Master)'!$G$2:$G$227,"Low") -> 6 | M31: =COUNTIFS('All Tickets (Master)'!$D$2:$D$227,$A31,'All Tickets (Master)'!$E$2:$E$227,$B31,'All Tickets (Master)'!$F$2:$F$227,"FE") -> 1 | N31: =COUNTIFS('All Tickets (Master)'!$D$2:$D$227,$A31,'All Tickets (Master)'!$E$2:$E$227,$B31,'All Tickets (Master)'!$F$2:$F$227,"BE") -> 4
B32: GRAND TOTAL | C32: =SUM(C4:C31) -> 225 | D32: =SUM(D4:D31) -> 181 | E32: =SUM(E4:E31) -> 21 | F32: =SUM(F4:F31) -> 6 | G32: =SUM(G4:G31) -> 8 | H32: =SUM(H4:H31) -> 9 | I32: =SUM(I4:I31) -> 30 | J32: =SUM(J4:J31) -> 111 | ... N32: =SUM(N4:N31) -> 29

Sheet All Tickets (Master)
A1: Issue Key | B1: Type | C1: Summary | D1: Area | E1: Caboodle Module | F1: FE/BE | G1: Priority | H1: Status | I1: Assignee | J1: Reporter | K1: Created | L1: Updated | M1: Due / Note
A2: CS-146 | B2: Task | C2: [BE] Module on off | D2: Admin | E2: Admin (General) | F2: BE | G2: Medium | H2: Backlog | I2: Bijoy Chandra Nath | J2: Md Mashiul Azam Chowdhury | K2: 12/3/2023 | L2: 12/3/2023 | M2: Discuss
A3: CS-147 | B3: Task | C3: [FE] Module on off | D3: Admin | E3: Admin (General) | F3: FE | G3: Medium | H3: Backlog | I3: Md Mashiul Azam Chowdhury | J3: Md Mashiul Azam Chowdhury | K3: 12/3/2023 | L3: 4/27/2025 | M3: Discuss
A4: CS-190 | B4: Task | C4: Caboodle Phase 2 Requirements | D4: Platform & Cross-Cutting | E4: Infrastructure / Cross-Cutting | F4: Unspec | G4: Medium | H4: Backlog | J4: Md Mashiul Azam Chowdhury | K4: 12/9/2023 | L4: 2/5/2024
A5: CS-234 | B5: Task | C5: [BE] Promotional Management - Push date submission to brand side | D5: Broker Dashboard | E5: Promotional Management | F5: BE | G5: Medium | H5: Backlog | I5: Bijoy Chandra Nath | J5: Md Mashiul Azam Chowdhury | K5: 12/21/2023 | L5: 12/21/2023 | M5: Discuss
A6: CS-232 | B6: Task | C6: [BE] Promotional Management - Published distributor pricing for Promo Submissions | D6: Broker Dashboard | E6: Promotional Management | F6: BE | G6: Low | H6: Backlog | I6: Bijoy Chandra Nath | J6: Md Mashiul Azam Chowdhury | K6: 12/21/2023 | L6: 12/21/2023 | M6: Discuss
A7: CS-245 | B7: Task | C7: [BE] Admin - Activity Log | D7: Admin | E7: Admin (General) | F7: BE | G7: Low | H7: Backlog | I7: Bijoy Chandra Nath | J7: Md Mashiul Azam Chowdhury | K7: 12/21/2023 | L7: 12/21/2023 | M7: Discuss
A8: CS-246 | B8: Task | C8: [FE] Admin - Activity Log | D8: Admin | E8: Admin (General) | F8: FE | G8: Low | H8: Backlog | I8: Md Mashiul Azam Chowdhury | J8: Md Mashiul Azam Chowdhury | K8: 12/21/2023 | L8: 4/27/2025 | M8: Discuss
A9: CS-247 | B9: Task | C9: [BE] Admin - Upload Effeciency | D9: Admin | E9: Admin (General) | F9: BE | G9: Low | H9: Backlog | I9: Bijoy Chandra Nath | J9: Md Mashiul Azam Chowdhury | K9: 12/21/2023 | L9: 12/21/2023 | M9: Discuss
A10: CS-280 | B10: Task | C10: [BE] Product Specs Add a text box for Shelf Life and another for Attributes. Doesn't need to be in the file upload | D10: Brand | E10: Product Specs | F10: BE | G10: Medium | H10: Backlog | I10: Bijoy Chandra Nath | J10: Md Mashiul Azam Chowdhury | K10: 1/1/2024 | L10: 1/1/2024 | M10: Don't Do
A11: CS-376 | B11: Task | C11: Product Specs - Add Chck Box for Manufacturer Discontinued | D11: Brand | E11: Product Specs | F11: Unspec | G11: Medium | H11: Backlog | I11: Md Mashiul Azam Chowdhury | J11: Constance Wolfe | K11: 2/10/2024 | L11: 4/27/2025 | M11: Complete?
A12: CS-405 | B12: Task | C12: Monitoring Service | D12: Platform & Cross-Cutting | E12: Infrastructure / Cross-Cutting | F12: Unspec | G12: Medium | H12: Backlog | I12: Bijoy Chandra Nath | J12: Bijoy Chandra Nath | K12: 2/29/2024 | L12: 9/25/2025 | M12: ??
A13: CS-478 | B13: Bug | C13: Product Specs Price List | Price Change is not flowing thru Trade Spend for promos after date change | D13: Brand | E13: Product Specs | F13: Unspec | G13: Highest | H13: Reopened | I13: Bijoy Chandra Nath | J13: Constance Wolfe | K13: 4/25/2024 | L13: 7/9/2024
A14: CS-487 | B14: Task | C14: [BE] Saving Banner SKU Failed Records and automatically adding them back into the system once we've matched up the unrecognized banners from the Data Mapping section | D14: Admin | E14: Data Mapping | F14: BE | G14: Medium | H14: Backlog | I14: Bijoy Chandra Nath | J14: Bijoy Chandra Nath | K14: 4/29/2024 | L14: 9/25/2025 | M14: ??
A15: CS-496 | B15: Bug | C15: Banner Upload Error Messaging | D15: Admin | E15: CRM Data Upload | F15: Unspec | G15: High | H15: Backlog | J15: Constance Wolfe | K15: 5/2/2024 | L15: 11/10/2025 | M15: ??
A16: CS-514 | B16: Task | C16: Optimize the tables to ensure that the site remains unaffected even with a large amount of data. | D16: Platform & Cross-Cutting | E16: Infrastructure / Cross-Cutting | F16: Unspec | G16: High | H16: Backlog | I16: Md Mashiul Azam Chowdhury | J16: Md Mashiul Azam Chowdhury | K16: 5/7/2024 | L16: 5/7/2024 | M16: Complete?
A17: CS-517 | B17: Task | C17: Apply Indexing Mechanism in Database | D17: Platform & Cross-Cutting | E17: Infrastructure / Cross-Cutting | F17: Unspec | G17: High | H17: In Progress | I17: Bijoy Chandra Nath | J17: Bijoy Chandra Nath | K17: 5/7/2024 | L17: 9/25/2025 | M17: Provide update
A18: CS-512 | B18: Task | C18: Check if we can further utilize caching from any other areas | D18: Platform & Cross-Cutting | E18: Infrastructure / Cross-Cutting | F18: Unspec | G18: Medium | H18: Backlog | I18: Md Mashiul Azam Chowdhury | J18: Md Mashiul Azam Chowdhury | K18: 5/7/2024 | L18: 5/7/2024 | M18: ??
A19: CS-518 | B19: Task | C19: Automatically Remove Deleted Records After Certain Period Of Time | D19: Platform & Cross-Cutting | E19: Infrastructure / Cross-Cutting | F19: Unspec | G19: Medium | H19: Backlog | I19: Bijoy Chandra Nath | J19: Bijoy Chandra Nath | K19: 5/7/2024 | L19: 9/25/2025 | M19: ??
A20: CS-519 | B20: Task | C20: [BE] Re-Structuring The Code Base | D20: Platform & Cross-Cutting | E20: Infrastructure / Cross-Cutting | F20: BE | G20: Medium | H20: In Progress | I20: Bijoy Chandra Nath | J20: Bijoy Chandra Nath | K20: 5/7/2024 | L20: 9/25/2025 | M20: Provide update
A21: CS-532 | B21: Task | C21: Trade Spend | Promo Event Details | Is it possible to add a sku without going thru the stepper again? | D21: Brand | E21: Trade Spend Sandbox | F21: Unspec | G21: Low | H21: Backlog | J21: Constance Wolfe | K21: 5/28/2024 | L21: 5/28/2024 | M21: Complete?
A22: CS-562 | B22: Task | C22: [BE] Implement User-Based Permission Control Module | D22: Admin | E22: User Management | F22: BE | G22: Medium | H22: In Progress | I22: Bijoy Chandra Nath | J22: Bijoy Chandra Nath | K22: 6/24/2024 | L22: 9/25/2025 | M22: Provide update
A23: CS-570 | B23: Task | C23: Filters Updates | D23: Platform & Cross-Cutting | E23: Infrastructure / Cross-Cutting | F23: Unspec | G23: Highest | H23: Reopened | I23: Md Mashiul Azam Chowdhury | J23: Heather Whittier | K23: 7/9/2024 | L23: 4/27/2025
A24: CS-617 | B24: Sub-task | C24: [BE] Manufacture Discontinue | MFR Disco Status | D24: Brand | E24: Product Specs | F24: BE | G24: High | H24: In Progress | I24: Bijoy Chandra Nath | J24: Md Mashiul Azam Chowdhury | K24: 9/26/2024 | L24: 1/7/2025 | M24: Provide update
A25: CS-653 | B25: Task | C25: Caboodle Broker | Trade Spend Sandbox should report to Promotional Management (not Promo Planning) | D25: Brand | E25: Trade Spend Sandbox | F25: Unspec | G25: High | H25: Ready for Production | I25: Bijoy Chandra Nath | J25: Constance Wolfe | K25: 11/26/2024 | L25: 11/6/2025 | M25: Provide update
A26: CS-658 | B26: Bug | C26: Files | Files Tree Display issues See image of overlapping folders | D26: Broker Dashboard | E26: Files | F26: Unspec | G26: High | H26: Backlog | I26: Md Mashiul Azam Chowdhury | J26: Constance Wolfe | K26: 12/6/2024 | L26: 4/27/2025 | M26: ??
A27: CS-675 | B27: Sub-task | C27: Empowering Brand owner's edit in Banner SKU section | D27: Admin | E27: Admin (General) | F27: Unspec | G27: High | H27: Backlog | I27: Bijoy Chandra Nath | J27: Md Mashiul Azam Chowdhury | K27: 12/26/2024 | L27: 9/25/2025 | M27: ??
A28: CS-688 | B28: Task | C28: [BE] Implement read tables for Market Overview | D28: Broker Dashboard | E28: Market Overview | F28: BE | G28: High | H28: In Progress | I28: Bijoy Chandra Nath | J28: Bijoy Chandra Nath | K28: 2/5/2025 | L28: 9/25/2025 | M28: Provide update
A29: CS-701 | B29: Story | C29: Share link of pages like in google and restrict it to view only | D29: Platform & Cross-Cutting | E29: Infrastructure / Cross-Cutting | F29: Unspec | G29: Low | H29: Backlog | I29: Constance Wolfe | J29: Md Mashiul Azam Chowdhury | K29: 2/17/2025 | L29: 11/6/2025 | M29: ??
A30: CS-725 | B30: Story | C30: Trade Spend Promotion Module | D30: Brand | E30: Trade Spend Sandbox | F30: Unspec | G30: Highest | H30: Backlog | I30: Md Mashiul Azam Chowdhury | J30: Bijoy Chandra Nath | K30: 3/12/2025 | L30: 3/12/2025 | M30: ??
A31: CS-894 | B31: Epic | C31: Issues from QA audit | D31: Platform & Cross-Cutting | E31: Infrastructure / Cross-Cutting | F31: QA | G31: Low | H31: Backlog | J31: Fariha Jabin | K31: 5/5/2025 | L31: 11/6/2025 | M31: ??
A32: CS-955 | B32: Epic | C32: UX Audit | D32: Platform & Cross-Cutting | E32: Infrastructure / Cross-Cutting | F32: Unspec | G32: High | H32: Backlog | I32: Abdullah Al Mahmud | J32: Md Mashiul Azam Chowdhury | K32: 5/15/2025 | L32: 11/6/2025 | M32: ??
A33: CS-973 | B33: Story | C33: Regression Test | D33: Platform & Cross-Cutting | E33: Infrastructure / Cross-Cutting | F33: QA | G33: Low | H33: Backlog | J33: Fariha Jabin | K33: 5/26/2025 | L33: 5/29/2025 | M33: ??
A34: CS-992 | B34: Sub-task | C34: [BE] Retailer details page - Category search returning irrelevant results | D34: Brand | E34: Retailers | F34: BE | G34: Low | H34: In Progress | I34: Bijoy Chandra Nath | J34: Fariha Jabin | K34: 6/4/2025 | L34: 9/25/2025 | M34: Provide update
A35: CS-1022 | B35: Bug | C35: Trade Spend Sandbox | Step 2 Category Issues | D35: Brand | E35: Trade Spend Sandbox | F35: Unspec | G35: High | H35: Reopened | I35: Md Mashiul Azam Chowdhury | J35: Constance Wolfe | K35: 6/21/2025 | L35: 11/10/2025
A36: CS-1032 | B36: Task | C36: [BE] Reports > Promoted Case Allowance -Please start | D36: Reports | E36: Reports (Unspecified) | F36: BE | G36: High | H36: In Progress | I36: Bijoy Chandra Nath | J36: Constance Wolfe | K36: 7/1/2025 | L36: 9/25/2025 | M36: Q1
A37: CS-1037 | B37: Bug | C37: [BE] No error message when uploading a blank file | D37: Admin | E37: CRM Data Upload | F37: BE | G37: Low | H37: Backlog | I37: Bijoy Chandra Nath | J37: Fariha Jabin | K37: 7/1/2025 | L37: 11/10/2025 | M37: Q1
A38: CS-1042 | B38: Bug | C38: banner edit modal  sometimes retailer name shows retailer id | D38: Admin | E38: CRM Data Upload | F38: Unspec | G38: Low | H38: Reopened | I38: Md Mashiul Azam Chowdhury | J38: Fariha Jabin | K38: 7/1/2025 | L38: 11/17/2025
A39: CS-1038 | B39: Bug | C39: [BE] Template files dont show required/mandatory fields | D39: Admin | E39: Admin (General) | F39: BE | G39: High | H39: Backlog | I39: Bijoy Chandra Nath | J39: Fariha Jabin | K39: 7/1/2025 | L39: 11/10/2025 | M39: Q1
A40: CS-1039 | B40: Bug | C40: [BE] Field mismatch between manual form and upload template | D40: Admin | E40: Admin (General) | F40: BE | G40: Medium | H40: Backlog | I40: Bijoy Chandra Nath | J40: Fariha Jabin | K40: 7/1/2025 | L40: 11/10/2025 | M40: Fixed?
A41: CS-1035 | B41: Epic | C41: Admin bug tickets | D41: Admin | E41: Admin (General) | F41: Unspec | G41: Low | H41: Backlog | J41: Fariha Jabin | K41: 7/1/2025 | L41: 7/14/2025
A42: CS-1036 | B42: Bug | C42: newly created items not appearing without refresh | D42: Platform & Cross-Cutting | E42: Infrastructure / Cross-Cutting | F42: Unspec | G42: Low | H42: Ready for Production | I42: Md Mashiul Azam Chowdhury | J42: Fariha Jabin | K42: 7/1/2025 | L42: 11/18/2025 | M42: Provide update
A43: CS-1040 | B43: Bug | C43: ui issue  button corners broken | D43: Platform & Cross-Cutting | E43: Infrastructure / Cross-Cutting | F43: Unspec | G43: Low | H43: Backlog | I43: Md Mashiul Azam Chowdhury | J43: Fariha Jabin | K43: 7/1/2025 | L43: 11/10/2025 | M43: Fixed?
A44: CS-1045 | B44: Bug | C44: brand name should be unique | D44: Admin | E44: Admin (General) | F44: Unspec | G44: Low | H44: Backlog | J44: Fariha Jabin | K44: 7/2/2025 | L44: 11/10/2025 | M44: Fixed?
A45: CS-1046 | B45: Bug | C45: brand description not fully visible if too long | D45: Admin | E45: Admin (General) | F45: Unspec | G45: Low | H45: Backlog | J45: Fariha Jabin | K45: 7/2/2025 | L45: 11/10/2025 | M45: Fixed?
A46: CS-1047 | B46: Bug | C46: blank file upload shows unclear error | D46: Admin | E46: Admin (General) | F46: Unspec | G46: Low | H46: Backlog | J46: Fariha Jabin | K46: 7/2/2025 | L46: 11/10/2025 | M46: Fixed?
A47: CS-1048 | B47: Bug | C47: brand upload template includes extra column | D47: Admin | E47: Admin (General) | F47: Unspec | G47: Low | H47: Backlog | J47: Fariha Jabin | K47: 7/2/2025 | L47: 11/10/2025 | M47: Q1
A48: CS-1049 | B48: Bug | C48: brand owner  email search filter not working | D48: Admin | E48: Admin (General) | F48: Unspec | G48: Low | H48: Backlog | J48: Fariha Jabin | K48: 7/2/2025 | L48: 11/10/2025 | M48: Q2
A49: CS-1050 | B49: Bug | C49: brand  export is not working | D49: Admin | E49: Admin (General) | F49: Unspec | G49: Low | H49: Backlog | J49: Fariha Jabin | K49: 7/2/2025 | L49: 11/10/2025 | M49: Q2
A50: CS-1059 | B50: Task | C50: crm module  delete option missing in all modules except banner | D50: Brand | E50: Pipeline | F50: Unspec | G50: Low | H50: Backlog | I50: Md Mashiul Azam Chowdhury | J50: Fariha Jabin | K50: 7/7/2025 | L50: 7/7/2025 | M50: ??
A51: CS-1065 | B51: Bug | C51: if sub brand ID is deactivated by admin, logged-in user can still access system | D51: Broker Dashboard | E51: Broker Dashboard (General) | F51: Unspec | G51: Low | H51: Backlog | J51: Fariha Jabin | K51: 7/9/2025 | L51: 11/10/2025 | M51: Q3
A52: CS-1062 | B52: Bug | C52: banner profile page: if name field empty, try to save, cant save, no error message shown | D52: Admin | E52: Admin (General) | F52: Unspec | G52: Low | H52: Backlog | J52: Fariha Jabin | K52: 7/9/2025 | L52: 11/10/2025 | M52: Fixed?
A53: CS-1063 | B53: Bug | C53: banner profile page: change password is not working | D53: Admin | E53: Admin (General) | F53: Unspec | G53: Low | H53: Backlog | J53: Fariha Jabin | K53: 7/9/2025 | L53: 11/10/2025 | M53: Fixed?
A54: CS-1064 | B54: Bug | C54: login: if password is less than 6 characters, sign-up fails with no error message | D54: Admin | E54: Admin (General) | F54: Unspec | G54: Low | H54: Backlog | J54: Fariha Jabin | K54: 7/9/2025 | L54: 11/10/2025 | M54: Q1
A55: CS-1072 | B55: Task | C55: [BE] Broker Dashboard> Update landing page to match Brand environments. Replace dashboard with Broker Logo | D55: Broker Dashboard | E55: Broker Dashboard (General) | F55: BE | G55: High | H55: Backlog | I55: Bijoy Chandra Nath | J55: Constance Wolfe | K55: 7/15/2025 | L55: 11/6/2025 | M55: Q2/Q3
A56: CS-1077 | B56: Task | C56: Product Specs Add Product Change Order & Names of Fields | D56: Brand | E56: Product Specs | F56: Unspec | G56: High | H56: Backlog | I56: Md Mashiul Azam Chowdhury | J56: Constance Wolfe | K56: 7/22/2025 | L56: 7/22/2025 | M56: Q2
A57: CS-1078 | B57: Bug | C57: Invite User - role - brand - Select All checkbox behaves incorrectly | D57: Admin | E57: User Management | F57: Unspec | G57: Low | H57: Backlog | J57: Fariha Jabin | K57: 7/22/2025 | L57: 11/10/2025 | M57: ??
A58: CS-1090 | B58: Task | C58: Editing and Pushing from Trade spend sandbox will update corresponding Promo Planning | D58: Brand | E58: Trade Spend Sandbox | F58: Unspec | G58: High | H58: Backlog | I58: Md Mashiul Azam Chowdhury | J58: Md Mashiul Azam Chowdhury | K58: 8/6/2025 | L58: 8/6/2025 | M58: Complete?
A59: CS-1092 | B59: Sub-task | C59: [FE] Editing and Pushing from Trade spend sandbox will update corresponding Promo Planning | D59: Brand | E59: Trade Spend Sandbox | F59: FE | G59: High | H59: Backlog | I59: Md Mashiul Azam Chowdhury | J59: Md Mashiul Azam Chowdhury | K59: 8/6/2025 | L59: 8/6/2025 | M59: Fixed?
A60: CS-1095 | B60: Bug | C60: [FE] Slight Glitch after editing a promo event | D60: Brand | E60: Trade Spend Sandbox | F60: FE | G60: High | H60: Backlog | I60: Md Mashiul Azam Chowdhury | J60: Md Mashiul Azam Chowdhury | K60: 8/8/2025 | L60: 10/20/2025 | M60: Complete?
A61: CS-1112 | B61: Task | C61: product category change causes pricing to show "pricing not set" | D61: Brand | E61: Product Specs | F61: Unspec | G61: Low | H61: Reopened | I61: Bijoy Chandra Nath | J61: Fariha Jabin | K61: 8/14/2025 | L61: 11/6/2025
A62: CS-1118 | B62: Bug | C62: CRM>Pipeline>Back Button Issue | D62: Brand | E62: Pipeline | F62: Unspec | G62: High | H62: Backlog | I62: Md Mashiul Azam Chowdhury | J62: Constance Wolfe | K62: 8/19/2025 | L62: 11/10/2025 | M62: Q2
A63: CS-1132 | B63: Bug | C63: When clicking the Add New Event button, the modal shows a visual glitch. | D63: Brand | E63: Trade Spend Sandbox | F63: Unspec | G63: Low | H63: Backlog | I63: Md Mashiul Azam Chowdhury | J63: Fariha Jabin | K63: 8/25/2025 | L63: 10/20/2025 | M63: Complete?
A64: CS-1150 | B64: Task | C64: CRM | Pipeline - Need Undo option in task edit | D64: Brand | E64: Pipeline | F64: Unspec | G64: Medium | H64: Backlog | I64: Md Mashiul Azam Chowdhury | J64: Constance Wolfe | K64: 8/29/2025 | L64: 9/25/2025 | M64: Q2
A65: CS-1149 | B65: Bug | C65: Reports | Category Review Uploads & Data Pushes | D65: Reports | E65: Category Review Report | F65: Unspec | G65: High | H65: Backlog | I65: Bijoy Chandra Nath | J65: Constance Wolfe | K65: 8/29/2025 | L65: 11/10/2025 | M65: CR Needs Discussion
A66: CS-1159 | B66: Bug | C66: Folders | Download causing Errors | D66: Broker Dashboard | E66: Files | F66: Unspec | G66: Highest | H66: Backlog | I66: Bijoy Chandra Nath | J66: Constance Wolfe | K66: 9/8/2025 | L66: 11/10/2025 | M66: See Ticket 1179
A67: CS-1162 | B67: Task | C67: [FE] Store Insight whole report delete by filter | D67: Reports | E67: Retail Reports | F67: FE | G67: High | H67: Reopened | I67: Md Mashiul Azam Chowdhury | J67: Md Mashiul Azam Chowdhury | K67: 9/10/2025 | L67: 11/6/2025
A68: CS-1163 | B68: Task | C68: Background job for All Export | D68: Platform & Cross-Cutting | E68: Infrastructure / Cross-Cutting | F68: Unspec | G68: High | H68: In Progress | I68: Bijoy Chandra Nath | J68: Md Mashiul Azam Chowdhury | K68: 9/10/2025 | L68: 11/6/2025 | M68: Provide update
A69: CS-1164 | B69: Task | C69: [FE] 30 MB max size message for import | D69: Platform & Cross-Cutting | E69: Infrastructure / Cross-Cutting | F69: FE | G69: High | H69: Backlog | I69: Md Mashiul Azam Chowdhury | J69: Md Mashiul Azam Chowdhury | K69: 9/10/2025 | L69: 11/6/2025 | M69: Q1
A70: CS-1166 | B70: Task | C70: [BE] Check email delivery status for new Sign up | D70: Platform & Cross-Cutting | E70: Infrastructure / Cross-Cutting | F70: BE | G70: Medium | H70: Backlog | I70: Bijoy Chandra Nath | J70: Md Mashiul Azam Chowdhury | K70: 9/10/2025 | L70: 11/6/2025 | M70: Complete?
A71: CS-1174 | B71: Task | C71: Trade Spend | Sandbox and Approved Have back button from results page take user to same year | D71: Brand | E71: Trade Spend Sandbox | F71: Unspec | G71: High | H71: Backlog | I71: Md Mashiul Azam Chowdhury | J71: Constance Wolfe | K71: 9/20/2025 | L71: 9/25/2025 | M71: Complete?
A72: CS-1177 | B72: Bug | C72: The "Everyday Allowance" field does not retain entered data when navigating back from later steps. | D72: Brand | E72: Trade Spend Sandbox | F72: Unspec | G72: High | H72: Ready for Production | I72: Md Mashiul Azam Chowdhury | J72: Fariha Jabin | K72: 9/22/2025 | L72: 11/18/2025 | M72: Provide update
A73: CS-1178 | B73: Task | C73: EDLP events look the same as other events; there should be a different color, tag, or indicator to easily identify EDLP events. | D73: Brand | E73: Trade Spend Sandbox | F73: Unspec | G73: Low | H73: Backlog | I73: Md Mashiul Azam Chowdhury | J73: Fariha Jabin | K73: 9/22/2025 | L73: 10/20/2025 | M73: Q2
A74: CS-1179 | B74: Bug | C74: Files | Downloads still have errors see details | D74: Broker Dashboard | E74: Files | F74: Unspec | G74: Highest | H74: Backlog | I74: Md Mashiul Azam Chowdhury | J74: Constance Wolfe | K74: 9/26/2025 | L74: 11/10/2025 | M74: Q1
A75: CS-1185 | B75: Bug | C75: TSS | Create an EDLP Promotion Only Creates Error | D75: Brand | E75: Trade Spend Sandbox | F75: Unspec | G75: High | H75: Backlog | I75: Md Mashiul Azam Chowdhury | J75: Constance Wolfe | K75: 10/1/2025 | L75: 11/10/2025 | M75: Fixed?
A76: CS-1186 | B76: Bug | C76: TSS | Duplicating a Promotion Issue- Comments are not included in the copy | D76: Brand | E76: Trade Spend Sandbox | F76: Unspec | G76: High | H76: Ready for Production | I76: Bijoy Chandra Nath | J76: Constance Wolfe | K76: 10/2/2025 | L76: 11/10/2025 | M76: Provide Update
A77: CS-1187 | B77: Bug | C77: Trade Spend Sandbox | Ad Fees Step 4 Issue| If multiple events are selected the Ad Fee is split among all items in all events | D77: Brand | E77: Trade Spend Sandbox | F77: Unspec | G77: High | H77: Backlog | I77: Md Mashiul Azam Chowdhury | J77: Constance Wolfe | K77: 10/4/2025 | L77: 11/10/2025 | M77: Q1
A78: CS-1190 | B78: Task | C78: Trade Spend Roll Up Report | Add Column for Total Trade Spend that Adds the TPR Spend w/ Ad/TPR Fees | D78: Reports | E78: Trade Spend Rollup | F78: Unspec | G78: Highest | H78: Backlog | I78: Md Mashiul Azam Chowdhury | J78: Constance Wolfe | K78: 10/11/2025 | L78: 10/11/2025 | M78: Q2
A79: CS-1192 | B79: Bug | C79: bugs relates to EDLP | D79: Brand | E79: Trade Spend Sandbox | F79: Unspec | G79: High | H79: In Staging | I79: Md Mashiul Azam Chowdhury | J79: Fariha Jabin | K79: 10/20/2025 | L79: 11/17/2025 | M79: Provide update
... A90: CS-1212 | B90: Bug | C90: TSS> Add EDLP to Existing Promotion > 2nd Pop Up Box only displays 1 Product | D90: Brand | E90: Trade Spend Sandbox | F90: Unspec | G90: Highest | H90: Ready for Production | I90: Md Mashiul Azam Chowdhury | J90: Constance Wolfe | K90: 11/5/2025 | L90: 12/22/2025 | M90: Provide Update
A91: CS-1223 | B91: Task | C91: Remove legacy SPINS data  keep only filtered, relevant datasets. | D91: Reports | E91: SPINS | F91: Unspec | G91: High | H91: Backlog | J91: Md Mashiul Azam Chowdhury | K91: 11/6/2025 | L91: 11/6/2025 | M91: Q1
A92: CS-1222 | B92: Task | C92: Build and validate the Single Distributor Report. | D92: Reports | E92: Distributor Report | F92: Unspec | G92: High | H92: In Progress | J92: Md Mashiul Azam Chowdhury | K92: 11/6/2025 | L92: 11/6/2025 | M92: In Progress
A93: CS-1214 | B93: Task | C93: Implement and test Crisp integration Or Data Scrapping (API connection, data sync). | D93: Admin | E93: Data Mapping | F93: Unspec | G93: High | H93: In Progress | I93: Bijoy Chandra Nath | J93: Md Mashiul Azam Chowdhury | K93: 11/6/2025 | L93: 11/24/2025 | M93: Complete?
A94: CS-1216 | B94: Task | C94: Data Mapping Expansion  Phase 2 | D94: Admin | E94: Data Mapping | F94: Unspec | G94: High | H94: In Progress | J94: Md Mashiul Azam Chowdhury | K94: 11/6/2025 | L94: 12/1/2025
A95: CS-1219 | B95: Task | C95: Integrate with the Data Mapping module to ensure mapped fields align during import/export. | D95: Admin | E95: Data Mapping | F95: Unspec | G95: High | H95: In Progress | J95: Md Mashiul Azam Chowdhury | K95: 11/6/2025 | L95: 11/6/2025 | M95: Complete?
A96: CS-1213 | B96: Task | C96: Resolve all email service reliability issues | D96: Platform & Cross-Cutting | E96: Infrastructure / Cross-Cutting | F96: Unspec | G96: High | H96: Backlog | I96: Bijoy Chandra Nath | J96: Md Mashiul Azam Chowdhury | K96: 11/6/2025 | L96: 11/24/2025 | M96: Complete?
A97: CS-1217 | B97: Task | C97: [BE] Implement the Upload/Download Wizard to handle imports/exports. | D97: Platform & Cross-Cutting | E97: Infrastructure / Cross-Cutting | F97: BE | G97: High | H97: Backlog | I97: Bijoy Chandra Nath | J97: Md Mashiul Azam Chowdhury | K97: 11/6/2025 | L97: 1/29/2026 | M97: Complete?
A98: CS-1218 | B98: Task | C98: Remove the 30MB upload restriction (target: 200MB+). | D98: Platform & Cross-Cutting | E98: Infrastructure / Cross-Cutting | F98: Unspec | G98: High | H98: Backlog | J98: Md Mashiul Azam Chowdhury | K98: 11/6/2025 | L98: 11/6/2025 | M98: Complete?
A99: CS-1220 | B99: Task | C99: Conduct end-to-end QA with real-world data samples. | D99: Platform & Cross-Cutting | E99: Infrastructure / Cross-Cutting | F99: QA | G99: High | H99: Backlog | J99: Md Mashiul Azam Chowdhury | K99: 11/6/2025 | L99: 11/6/2025 | M99: Q1
A100: CS-1221 | B100: Task | C100: Integrate Tableau Reporting into the platform. | D100: Platform & Cross-Cutting | E100: Infrastructure / Cross-Cutting | F100: Unspec | G100: High | H100: Backlog | J100: Md Mashiul Azam Chowdhury | K100: 11/6/2025 | L100: 11/6/2025 | M100: Not Doing
A101: CS-1224 | B101: Task | C101: Conduct year-end QA, finalize documentation, and prepare release packages. | D101: Platform & Cross-Cutting | E101: Infrastructure / Cross-Cutting | F101: QA | G101: High | H101: Backlog | J101: Md Mashiul Azam Chowdhury | K101: 11/6/2025 | L101: 11/6/2025 | M101: Q1
A102: CS-1225 | B102: Task | C102: CRM > Distributor > Unlink Banner > Remove restriction that it's tied up in a Promotion | D102: Brand | E102: Distributors | F102: Unspec | G102: Highest | H102: In Progress | I102: Bijoy Chandra Nath | J102: Constance Wolfe | K102: 11/8/2025 | L102: 11/11/2025 | M102: Provide Update
A103: CS-1230 | B103: Task | C103: Reports>Trade Spend Roll Up > Updates on Headers (Net to Gross) + other Minor Changes | D103: Reports | E103: Trade Spend Rollup | F103: Unspec | G103: High | H103: Backlog | I103: Md Mashiul Azam Chowdhury | J103: Constance Wolfe | K103: 11/17/2025 | L103: 11/17/2025 | M103: Still some items to complete
A104: CS-1236 | B104: Bug | C104: TSS- New bugs | D104: Brand | E104: Trade Spend Sandbox | F104: Unspec | G104: High | H104: Backlog | I104: Bijoy Chandra Nath | J104: Fariha Jabin | K104: 11/27/2025 | L104: 12/9/2025 | M104: Complete?
A105: CS-1240 | B105: Task | C105: Trade Spend Calculations | D105: Brand | E105: Trade Spend Sandbox | F105: Unspec | G105: Highest | H105: Backlog | I105: Bijoy Chandra Nath | J105: Constance Wolfe | K105: 12/11/2025 | L105: 12/11/2025 | M105: Complete?
A106: CS-1239 | B106: Task | C106: [BE] Forecast related endpoint implementation (Export) | D106: Platform & Cross-Cutting | E106: Infrastructure / Cross-Cutting | F106: BE | G106: Highest | H106: In Progress | I106: Bijoy Chandra Nath | J106: Bijoy Chandra Nath | K106: 12/11/2025 | L106: 12/11/2025 | M106: Provide Update
A107: CS-1244 | B107: Bug | C107: TSS Details Page: Pricing, Allowance, Total Spend, Alert UI, and TPR Fee Calculation Issues | D107: Brand | E107: Trade Spend Sandbox | F107: Unspec | G107: High | H107: Backlog | I107: Bijoy Chandra Nath | J107: Fariha Jabin | K107: 12/24/2025 | L107: 12/24/2025 | M107: Q1
A108: CS-1246 | B108: Task | C108: [BE] Add Gross Unit Calculation in Roll up report | D108: Reports | E108: Trade Spend Rollup | F108: BE | G108: High | H108: In Progress | I108: Bijoy Chandra Nath | J108: Bijoy Chandra Nath | K108: 12/24/2025 | L108: 12/24/2025 | M108: ??
A109: CS-1248 | B109: Task | C109: TSS> Add Ad Fees/TPR Fees (Lump Sum) that's not associated with any promotion | D109: Brand | E109: Trade Spend Sandbox | F109: Unspec | G109: High | H109: Backlog | I109: Md Mashiul Azam Chowdhury | J109: Constance Wolfe | K109: 12/29/2025 | L109: 12/29/2025 | M109: Q1
A110: CS-1254 | B110: Bug | C110: [BE] Trade Spend Sandbox - New & Discontinued Items Not Calculating according to Add & Disco. Date | D110: Brand | E110: Trade Spend Sandbox | F110: BE | G110: Highest | H110: In Staging | I110: Bijoy Chandra Nath | J110: Constance Wolfe | K110: 1/9/2026 | L110: 1/20/2026
...

Sheet Broker Dashboard
A1: Broker Dashboard — 33 tickets
A3: Issue Key | B3: Type | C3: Summary | D3: Area | E3: Caboodle Module | F3: FE/BE | G3: Priority | H3: Status | I3: FE | J3: BE | K3: QA | L3: Assignee | M3: Reporter | N3: Created | O3: Updated | P3: Due / Note
A4: ▸ Market Overview (6)
A5: CS-1299 | C5: Broker Dashboard Updates > APL + Add Log Market Overview | D5: Broker Dashboard | E5: Market Overview | F5: Unspec | G5: High | H5: Backlog | L5: Md Mashiul Azam Chowdhury Efti | M5: Constance Wolfe | N5: 3/31/2026 | O5: 5/4/2026 | P5: STORY 1326
C6: Moved to Brand Mondule (Home Page)
A7: CS-1310 | C7: Broker Dashboard Market Overview > Store List Not populating | D7: Broker Dashboard | E7: Market Overview | F7: Unspec | G7: High | H7: Backlog | I7: 30m | J7: 1h | K7: 30m | L7: Bijoy Chandra Nath | M7: Constance Wolfe | N7: 3/31/2026 | O7: 5/4/2026 | P7: STORY 1326
A8: CS-1318 | C8: Broker Dashboard | Market Overview Filter Needs more Field Options List Too Limited | D8: Broker Dashboard | E8: Market Overview | F8: Unspec | G8: High | H8: Backlog | I8: 3h | J8: 2h | K8: 1h | L8: Bijoy Chandra Nath | M8: Constance Wolfe | N8: 4/2/2026 | O8: 5/4/2026 | P8: STORY 1326
A9: CS-1326 | C9: Enhance Broker Dashboard Market Overview Functionality | D9: Broker Dashboard | E9: Market Overview | F9: Unspec | G9: High | H9: Backlog | L9: Md Mashiul Azam Chowdhury Efti | M9: Md Mashiul Azam Chowdhury Efti | N9: 4/7/2026 | O9: 5/4/2026 | P9: STORY
A10: CS-688 | B10: Task | C10: [BE] Implement read tables for Market Overview | D10: Broker Dashboard | E10: Market Overview | F10: BE | G10: High | H10: In Progress | J10: 4h | K10: 2h | L10: Bijoy Chandra Nath | M10: Bijoy Chandra Nath | N10: 2/5/2025 | O10: 9/25/2025 | P10: Provide update
A11: ▸ Promotional Management (5)
A12: CS-1324 | C12: Broker Dashboard | Promotional Management Only push Brand Approved Promotions to Promo Management | D12: Broker Dashboard | E12: Promotional Management | F12: Unspec | G12: High | H12: Backlog | J12: 2h | K12: 1h | L12: Bijoy Chandra Nath | M12: Constance Wolfe | N12: 4/3/2026 | O12: 5/4/2026 | P12: STORY 1328
A13: CS-1328 | C13: Improve Broker Promotional Management Export and Approval Flow | D13: Broker Dashboard | E13: Promotional Management | F13: Unspec | G13: High | H13: Backlog | L13: Md Mashiul Azam Chowdhury Efti | M13: Md Mashiul Azam Chowdhury Efti | N13: 4/7/2026 | O13: 5/4/2026 | P13: STORY
A14: CS-1367 | C14: Broker Dashboard Promo Management | Export Data Does not Match Filter Data (Does not work at all) | D14: Broker Dashboard | E14: Promotional Management | F14: Unspec | G14: High | H14: Backlog | J14: 3h | K14: 1h | L14: Md Mashiul Azam Chowdhury Efti | M14: Constance Wolfe | N14: 5/2/2026 | O14: 5/2/2026
A15: CS-234 | B15: Task | C15: [BE] Promotional Management - Push date submission to brand side | D15: Broker Dashboard | E15: Promotional Management | F15: BE | G15: Medium | H15: Backlog | L15: Bijoy Chandra Nath | M15: Md Mashiul Azam Chowdhury | N15: 12/21/2023 | O15: 12/21/2023
A16: CS-232 | B16: Task | C16: [BE] Promotional Management - Published distributor pricing for Promo Submissions | D16: Broker Dashboard | E16: Promotional Management | F16: BE | G16: Low | H16: Backlog | L16: Bijoy Chandra Nath | M16: Md Mashiul Azam Chowdhury | N16: 12/21/2023 | O16: 12/21/2023
A17: ▸ Category Review (11)
A18: CS-1417 | B18: In Staging | C18: Broker Dashboard | Category Review Filter & Upload Issues | D18: Broker Dashboard | E18: Category Review | F18: Unspec | G18: Highest | H18: Backlog | L18: Bijoy Chandra Nath | M18: Constance Wolfe | N18: 5/30/2026 | O18: 6/4/2026
A19: CS-1296 | B19: Done | C19: Broker Dashboard | Category Review Calendar Rollup | D19: Broker Dashboard | E19: Category Review | F19: Unspec | G19: High | H19: Backlog | L19: Bijoy Chandra Nath | M19: Constance Wolfe | N19: 3/31/2026 | O19: 5/28/2026 | P19: STORY 1327
A20: CS-1315 | B20: Done | C20: Category Review | Export All Data only Exports the current Page | D20: Broker Dashboard | E20: Category Review | F20: Unspec | G20: High | H20: In Progress | L20: Bijoy Chandra Nath | M20: Constance Wolfe | N20: 4/2/2026 | O20: 5/5/2026 | P20: STORY 1330
A21: CS-1316 | C21: Category Review | Implement Scrolling vs pages | D21: Broker Dashboard | E21: Category Review | F21: Unspec | G21: High | H21: Backlog | I21: 2h | K21: 10m | L21: Md Mashiul Azam Chowdhury Efti | M21: Constance Wolfe | N21: 4/2/2026 | O21: 5/4/2026 | P21: STORY 1330
A22: CS-1317 | B22: Redundend | C22: Category Review | UI/UX Consider more modern look/feel See sample | D22: Broker Dashboard | E22: Category Review | F22: Unspec | G22: High | H22: Backlog | L22: Md Mashiul Azam Chowdhury Efti | M22: Constance Wolfe | N22: 4/2/2026 | O22: 5/4/2026 | P22: STORY 1330 This Example is a Loveable Design for a new functionality
A23: CS-1319 | B23: Done | C23: Category Review | Adding Retailers with multiple Reviews Produces Duplicates of the Retailer in the Filter (Also see CS-1320) | D23: Broker Dashboard | E23: Category Review | F23: Unspec | G23: High | H23: Backlog | L23: Md Mashiul Azam Chowdhury Efti | M23: Constance Wolfe | N23: 4/3/2026 | O23: 4/3/2026
A24: CS-1320 | B24: Done | C24: Category Review | Add Log Error Invalid Month Even though the month is Valid | D24: Broker Dashboard | E24: Category Review | F24: Unspec | G24: High | H24: Reopened | L24: Bijoy Chandra Nath | M24: Constance Wolfe | N24: 4/3/2026 | O24: 5/18/2026
A25: CS-1329 | C25: Fix Category Review Data Isolation and Upload Issues | D25: Broker Dashboard | E25: Category Review | F25: Unspec | G25: High | H25: Backlog | L25: Bijoy Chandra Nath | M25: Md Mashiul Azam Chowdhury Efti | N25: 4/7/2026 | O25: 5/4/2026
A26: CS-1330 | C26: Improve Category Review UX, Navigation and Export | D26: Broker Dashboard | E26: Category Review | F26: Unspec | G26: High | H26: Backlog | L26: Md Mashiul Azam Chowdhury Efti | M26: Md Mashiul Azam Chowdhury Efti | N26: 4/7/2026 | O26: 5/4/2026 | P26: STORY
A27: CS-1361 | B27: Redundend | C27: Broker Dashboard | New Category Review Functionality | D27: Broker Dashboard | E27: Category Review | F27: Unspec | G27: High | H27: Backlog | L27: Bijoy Chandra Nath | M27: Constance Wolfe | N27: 4/29/2026 | O27: 6/17/2026 | P27: SEE Ticket 1317
A28: CS-1423 | B28: Done | C28: Broker Dashboard | Category Review Propagation | D28: Broker Dashboard | E28: Category Review | F28: Unspec | G28: High | H28: Backlog | L28: Bijoy Chandra Nath | M28: Constance Wolfe | N28: 6/20/2026 | O28: 6/21/2026
A29: ▸ Distributor APL (4)
A30: CS-1424 | B30: Task | C30: Data Mapping | Broker Dashboard APL | Need Data Sync for Broker Distributor APL | D30: Broker Dashboard | E30: Distributor APL | F30: Unspec | G30: Highest | H30: Backlog | I30: 2h | J30: 6d | L30: Md Mashiul Azam Chowdhury Efti | M30: Constance Wolfe | N30: 6/23/2026 | O30: 6/23/2026
A31: CS-1363 | C31: Broker Dashboard | APL Add Distributor & Product (make dependent to brand) to the Filter | D31: Broker Dashboard | E31: Distributor APL | F31: Unspec | G31: High | H31: Backlog | I31: 2h | J31: 4h | K31: 1h | L31: Md Mashiul Azam Chowdhury Efti | M31: Constance Wolfe | N31: 4/29/2026 | O31: 4/29/2026
A32: CS-1403 | C32: Broker Dashboard | APL Upload Adjust for UNFI UPC Codes | D32: Broker Dashboard | E32: Distributor APL | F32: Unspec | G32: High | H32: Backlog | J32: 4h | K32: 1h | L32: Md Mashiul Azam Chowdhury Efti | M32: Constance Wolfe | N32: 5/13/2026 | O32: 5/13/2026
A33: CS-1408 | C33: Broker Dashboard > APL Report > Filter showing multiple listings for same item | D33: Broker Dashboard | E33: Distributor APL | F33: Unspec | G33: High | H33: Backlog | J33: CS-1363 | L33: Md Mashiul Azam Chowdhury Efti | M33: Constance Wolfe | N33: 5/20/2026 | O33: 5/20/2026
A34: ▸ Files (3)
A35: CS-1159 | B35: Bug | C35: Folders | Download causing Errors | D35: Broker Dashboard | E35: Files | F35: Unspec | G35: Highest | H35: Backlog | L35: Bijoy Chandra Nath | M35: Constance Wolfe | N35: 9/8/2025 | O35: 11/10/2025 | P35: See Ticket 1179
A36: CS-1179 | B36: Bug | C36: Files | Downloads still have errors see details | D36: Broker Dashboard | E36: Files | F36: Unspec | G36: Highest | H36: Backlog | L36: Md Mashiul Azam Chowdhury | M36: Constance Wolfe | N36: 9/26/2025 | O36: 11/10/2025 | P36: Q1
A37: CS-658 | B37: Bug | C37: Files | Files Tree Display issues See image of overlapping folders | D37: Broker Dashboard | E37: Files | F37: Unspec | G37: High | H37: Backlog | I37: 4h | K37: 30m | L37: Md Mashiul Azam Chowdhury | M37: Constance Wolfe | N37: 12/6/2024 | O37: 4/27/2025 | P37: ??
A38: ▸ Broker Dashboard (General) (4)
A39: CS-1072 | B39: Task | C39: [BE] Broker Dashboard> Update landing page to match Brand environments. Replace dashboard with Broker Logo | D39: Broker Dashboard | E39: Broker Dashboard (General) | F39: BE | G39: High | H39: Backlog | L39: Bijoy Chandra Nath | M39: Constance Wolfe | N39: 7/15/2025 | O39: 11/6/2025 | P39: Q2/Q3
A40: CS-1305 | C40: Broker Dashboard Update UI to match the rest of the platform | D40: Broker Dashboard | E40: Broker Dashboard (General) | F40: Unspec | G40: High | H40: Backlog | L40: Md Mashiul Azam Chowdhury Efti | M40: Constance Wolfe | N40: 3/31/2026 | O40: 3/31/2026
A41: CS-1327 | C41: Fix Broker Dashboard Navigation and UI Issues | D41: Broker Dashboard | E41: Broker Dashboard (General) | F41: Unspec | G41: High | H41: Backlog | L41: Bijoy Chandra Nath | M41: Md Mashiul Azam Chowdhury Efti | N41: 4/7/2026 | O41: 5/4/2026
A42: CS-1065 | B42: Bug | C42: if sub brand ID is deactivated by admin, logged-in user can still access system | D42: Broker Dashboard | E42: Broker Dashboard (General) | F42: Unspec | G42: Low | H42: Backlog | M42: Fariha Jabin | N42: 7/9/2025 | O42: 11/10/2025 | P42: Q3
A44: Need
C45: SUMMARY | D45: Area
C46: BROKER DASHBOARD
B47: 46223 | C47: Caboodle Dashboard update for CS 1324 CW Made Edits | D47: Broker Dashboarad | E47: CS-1324: Broker Dashboard | Promotional Management Only push Brand Approved Promotions to Promo Management
A48: CS-1072 | B48: 46223 | C48: [BE] Broker Dashboard> Update landing page to match Brand environments. Replace dashboard with Broker Logo | D48: Broker Dashboarad
C49: ASK CABOODLE | D49: Broker Dashboarad
B50: BD1 | C50: Dashboard Tasks | D50: Broker Dashboarad
B51: BD2 | C51: Assign time and person | D51: Broker Dashboarad
B52: BD3 | C52: Dashboard Filter My tasks or contact name | D52: Broker Dashboarad
B53: PM7 | C53: Broker Dashboard Button should have Broker Logo | E53: CW NEEDS TO REVIEW
B54: BD4 | C54: Pipeline in Broker Dashboard | D54: NEW
C56: CATEGORY REVIEW
B57: CR1 | C57: Remove all Reviews at once rather than page by page | D57: Category Review | E57: Complete
C58: Category Review Email Notification See link https://lovable.dev/projects/932320d2-ce2b-4b52-ad38-ba5a2a214dc1 | D58: Category Review
B59: CR3 | C59: Allow user to increase the rows at the bottom (infinenate Scroll) | D59: Catgegory Review | E59: Ticket 1316
A60: CR4 | B60: 46223 | C60: Calendar Sort by Banner or Category? | E60: Both are typed Question (rather than User Story) since they're explicitly open questions, and both link to the relevant existing tickets (CS-1296, CS-1316, CS-1361, CR4). Not yet committed.
A61: CR5 | B61: 46223 | C61: Category Review List now has Review End Date: Do we need to change the upload template?
C63: DISTRIBUTOR APL
B64: DA1 | C64: Allow infinite scrolling | D64: Distributor APL
B65: DA2 | C65: Edit requires a Wholesale Case Cost But Does not require that information during the Upload | D65: Distributor APL
C67: MARKET OVERVIEW
B68: MO1 | C68: Edit Log needs to allow user to edit: DC | D68: Market Overview
B69: MO2 | C69: Search Option? | D69: Market Overview
B70: MO3 | C70: Check and confirm Heirarchy of Status Upldates to Brand CRM | D70: Market Overview | E70: CW NEEDS TO REVIEW
B71: MO4 | C71: Number of Stores (Reporting Banner Door Count) This can be misleading KeHE/UNFI Independents = # Entered? | D71: Market Overview | E71: CW NEEDS TO REVIEW
B72: MO5 | C72: Add Log Ensure user can enter multiple stores | D72: Market Overview | E72: CW NEEDS TO REVIEW
B73: MO6 | C73: Add Log Consider Entering 1 Retailer/Multiple Brands | D73: Market Overview
C74: Add Log Does Distribution Center need to be Required? | D74: Market Overview
C75: Editing the Comment in the Log Can this Add new rather than override? | D75: Market Overview
C76: Push Updates to Brands via Email (Summary click here for details) | D76: Market Overview
C77: PROMO MANAGEMENT
A78: PM7 (BUG) | B78: NEED | C78: Submission Button Does not work | D78: Promotional Management
B79: PM2 | C79: Export Push to a Formatted Report Option (to save user from exporting then formatting) | D79: Promotional Management | E79: CW NEEDS TO REVIEW
B80: PM3 | C80: Implement Promo Status Options currurently found in Brand Promo Calendars (Active/Cancelled/Pending/Did Not Run/Declined/Retailer Approved/Completed/Submitted)in the Submission Button. Currently this is activated in TSS) Tagged by User login | D80: Promotional Management | E80: CW NEEDS TO REVIEW
B81: PM4 | C81: Notes Section (On top) : Allow User to Pin or Freeze Filter Options Example Useful for the year so user doesn't have to filter for the current year everytime the access the page) | D81: Promotional Management | E81: CW NEEDS TO REVIEW
B82: PM5 | C82: Format the Grid more uniformily (each month is a difference size) | D82: Promotional Management | E82: CW NEEDS TO REVIEW
B83: PM6 | C83: Allow the Event to move across months if the dates span multiple months | D83: Promotional Management | E83: CW NEEDS TO REVIEW

Sheet Brand Modules
A1: Brand — 56 tickets
A3: Issue Key | B3: Type | C3: Summary | D3: Area | E3: Caboodle Module | F3: FE/BE | G3: Priority | H3: Status | I3: Assignee | J3: Reporter | K3: Created | L3: Updated | M3: Due / Note
A4: ▸ Product Specs (8)
A5: CS-478 | B5: Bug | C5: Product Specs Price List | Price Change is not flowing thru Trade Spend for promos after date change | D5: Brand | E5: Product Specs | F5: Unspec | G5: Highest | H5: Reopened | I5: Bijoy Chandra Nath | J5: Constance Wolfe | K5: 4/25/2024 | L5: 7/9/2024
A6: CS-1077 | B6: Task | C6: Product Specs Add Product Change Order & Names of Fields | D6: Brand | E6: Product Specs | F6: Unspec | G6: High | H6: Backlog | I6: Md Mashiul Azam Chowdhury | J6: Constance Wolfe | K6: 7/22/2025 | L6: 7/22/2025 | M6: Q2
A7: CS-1386 | C7: Product Specs | Reorganize Tabs to this order: Categories > Products > Pricing | D7: Brand | E7: Product Specs | F7: Unspec | G7: High | H7: Backlog | I7: Md Mashiul Azam Chowdhury Efti | J7: Constance Wolfe | K7: 5/11/2026 | L7: 5/11/2026 | M7: Complete
A8: CS-1400 | C8: Product Specs | Updating Spec UPC Code causing Error | D8: Brand | E8: Product Specs | F8: Unspec | G8: High | H8: Backlog | I8: Md Mashiul Azam Chowdhury Efti | J8: Constance Wolfe | K8: 5/13/2026 | L8: 5/13/2026
A9: CS-617 | B9: Sub-task | C9: [BE] Manufacture Discontinue | MFR Disco Status | D9: Brand | E9: Product Specs | F9: BE | G9: High | H9: In Progress | I9: Bijoy Chandra Nath | J9: Md Mashiul Azam Chowdhury | K9: 9/26/2024 | L9: 1/7/2025 | M9: Provide update
A10: CS-280 | B10: Task | C10: [BE] Product Specs Add a text box for Shelf Life and another for Attributes. Doesn't need to be in the file upload | D10: Brand | E10: Product Specs | F10: BE | G10: Medium | H10: Backlog | I10: Bijoy Chandra Nath | J10: Md Mashiul Azam Chowdhury | K10: 1/1/2024 | L10: 1/1/2024 | M10: Don't Do
A11: CS-376 | B11: Task | C11: Product Specs - Add Chck Box for Manufacturer Discontinued | D11: Brand | E11: Product Specs | F11: Unspec | G11: Medium | H11: Backlog | I11: Md Mashiul Azam Chowdhury | J11: Constance Wolfe | K11: 2/10/2024 | L11: 4/27/2025 | M11: Complete?
A12: CS-1112 | B12: Task | C12: product category change causes pricing to show "pricing not set" | D12: Brand | E12: Product Specs | F12: Unspec | G12: Low | H12: Reopened | I12: Bijoy Chandra Nath | J12: Fariha Jabin | K12: 8/14/2025 | L12: 11/6/2025
A13: ▸ Distributors (1)
A14: CS-1225 | B14: Task | C14: CRM > Distributor > Unlink Banner > Remove restriction that it's tied up in a Promotion | D14: Brand | E14: Distributors | F14: Unspec | G14: Highest | H14: In Progress | I14: Bijoy Chandra Nath | J14: Constance Wolfe | K14: 11/8/2025 | L14: 11/11/2025 | M14: Provide Update
A15: ▸ Retailers (3)
A16: CS-1211 | B16: Task | C16: [BE] CRM - Retailers> Banner Activities Newest Dates at the top of the list | D16: Brand | E16: Retailers | F16: BE | G16: Highest | H16: In Staging | I16: Bijoy Chandra Nath | J16: Bijoy Chandra Nath | K16: 11/4/2025 | L16: 11/5/2025 | M16: Provide Update
A17: CS-1199 | B17: Bug | C17: CRM> Retailers>Promo $Rules> Upload option doesn't work> Other Notes in Description | D17: Brand | E17: Retailers | F17: Unspec | G17: Medium | H17: Backlog | I17: Md Mashiul Azam Chowdhury | J17: Constance Wolfe | K17: 10/23/2025 | L17: 11/10/2025 | M17: Q2
A18: CS-992 | B18: Sub-task | C18: [BE] Retailer details page - Category search returning irrelevant results | D18: Brand | E18: Retailers | F18: BE | G18: Low | H18: In Progress | I18: Bijoy Chandra Nath | J18: Fariha Jabin | K18: 6/4/2025 | L18: 9/25/2025 | M18: Provide update
A19: ▸ Contacts (1)
A20: CS-1369 | C20: CRM Contacts | Include title with the name | D20: Brand | E20: Contacts | F20: Unspec | G20: Medium | H20: Backlog | I20: Md Mashiul Azam Chowdhury Efti | J20: Constance Wolfe | K20: 5/2/2026 | L20: 5/2/2026
A21: ▸ Pipeline (5)
A22: CS-1118 | B22: Bug | C22: CRM>Pipeline>Back Button Issue | D22: Brand | E22: Pipeline | F22: Unspec | G22: High | H22: Backlog | I22: Md Mashiul Azam Chowdhury | J22: Constance Wolfe | K22: 8/19/2025 | L22: 11/10/2025 | M22: Q2
A23: CS-1348 | C23: CRM | Pipeline - Formatting Issue - Items cut off | D23: Brand | E23: Pipeline | F23: Unspec | G23: High | H23: Backlog | I23: Md Mashiul Azam Chowdhury Efti | J23: Constance Wolfe | K23: 4/21/2026 | L23: 4/21/2026
A24: CS-1349 | C24: CRM Pipeline | Enhance Editing Widget | D24: Brand | E24: Pipeline | F24: Unspec | G24: High | H24: Backlog | I24: Md Mashiul Azam Chowdhury Efti | J24: Constance Wolfe | K24: 4/21/2026 | L24: 4/21/2026
A25: CS-1150 | B25: Task | C25: CRM | Pipeline - Need Undo option in task edit | D25: Brand | E25: Pipeline | F25: Unspec | G25: Medium | H25: Backlog | I25: Md Mashiul Azam Chowdhury | J25: Constance Wolfe | K25: 8/29/2025 | L25: 9/25/2025 | M25: Q2
A26: CS-1425 | B26: Task | C26: CRM>Pipeline > Change Plan to Project > Hide/Archive Option > See Details | D26: Brand | E26: CRM Pipeline | G26: High | H26: Backlog | I26: Md Mashiul Azam Chowdhury Efti | J26: Constance Wolfe | K26: 46200.088 | L26: 46200.088
A27: CS-1059 | B27: Task | C27: crm module  delete option missing in all modules except banner | D27: Brand | E27: Pipeline | F27: Unspec | G27: Low | H27: Backlog | I27: Md Mashiul Azam Chowdhury | J27: Fariha Jabin | K27: 7/7/2025 | L27: 7/7/2025 | M27: ??
A28: ▸ Trade Spend Sandbox (37)
A29: CS-1209 | B29: Bug | C29: TSS> Add A Sku to Existing Issues | D29: Brand | E29: Trade Spend Sandbox | F29: Unspec | G29: Highest | H29: In Staging | I29: Md Mashiul Azam Chowdhury | J29: Constance Wolfe | K29: 11/1/2025 | L29: 12/22/2025 | M29: Provide Update
A30: CS-1212 | B30: Bug | C30: TSS> Add EDLP to Existing Promotion > 2nd Pop Up Box only displays 1 Product | D30: Brand | E30: Trade Spend Sandbox | F30: Unspec | G30: Highest | H30: Ready for Production | I30: Md Mashiul Azam Chowdhury | J30: Constance Wolfe | K30: 11/5/2025 | L30: 12/22/2025 | M30: Provide Update
A31: CS-1240 | B31: Task | C31: Trade Spend Calculations | D31: Brand | E31: Trade Spend Sandbox | F31: Unspec | G31: Highest | H31: Backlog | I31: Bijoy Chandra Nath | J31: Constance Wolfe | K31: 12/11/2025 | L31: 12/11/2025 | M31: Complete?
A32: CS-1254 | B32: Bug | C32: [BE] Trade Spend Sandbox - New & Discontinued Items Not Calculating according to Add & Disco. Date | D32: Brand | E32: Trade Spend Sandbox | F32: BE | G32: Highest | H32: In Staging | I32: Bijoy Chandra Nath | J32: Constance Wolfe | K32: 1/9/2026 | L32: 1/20/2026
A33: CS-725 | B33: Story | C33: Trade Spend Promotion Module | D33: Brand | E33: Trade Spend Sandbox | F33: Unspec | G33: Highest | H33: Backlog | I33: Md Mashiul Azam Chowdhury | J33: Bijoy Chandra Nath | K33: 3/12/2025 | L33: 3/12/2025 | M33: ??
A34: CS-1022 | B34: Bug | C34: Trade Spend Sandbox | Step 2 Category Issues | D34: Brand | E34: Trade Spend Sandbox | F34: Unspec | G34: High | H34: Reopened | I34: Md Mashiul Azam Chowdhury | J34: Constance Wolfe | K34: 6/21/2025 | L34: 11/10/2025
A35: CS-1090 | B35: Task | C35: Editing and Pushing from Trade spend sandbox will update corresponding Promo Planning | D35: Brand | E35: Trade Spend Sandbox | F35: Unspec | G35: High | H35: Backlog | I35: Md Mashiul Azam Chowdhury | J35: Md Mashiul Azam Chowdhury | K35: 8/6/2025 | L35: 8/6/2025 | M35: Complete?
A36: CS-1092 | B36: Sub-task | C36: [FE] Editing and Pushing from Trade spend sandbox will update corresponding Promo Planning | D36: Brand | E36: Trade Spend Sandbox | F36: FE | G36: High | H36: Backlog | I36: Md Mashiul Azam Chowdhury | J36: Md Mashiul Azam Chowdhury | K36: 8/6/2025 | L36: 8/6/2025 | M36: Fixed?
A37: CS-1095 | B37: Bug | C37: [FE] Slight Glitch after editing a promo event | D37: Brand | E37: Trade Spend Sandbox | F37: FE | G37: High | H37: Backlog | I37: Md Mashiul Azam Chowdhury | J37: Md Mashiul Azam Chowdhury | K37: 8/8/2025 | L37: 10/20/2025 | M37: Complete?
A38: CS-1174 | B38: Task | C38: Trade Spend | Sandbox and Approved Have back button from results page take user to same year | D38: Brand | E38: Trade Spend Sandbox | F38: Unspec | G38: High | H38: Backlog | I38: Md Mashiul Azam Chowdhury | J38: Constance Wolfe | K38: 9/20/2025 | L38: 9/25/2025 | M38: Complete?
A39: CS-1177 | B39: Bug | C39: The "Everyday Allowance" field does not retain entered data when navigating back from later steps. | D39: Brand | E39: Trade Spend Sandbox | F39: Unspec | G39: High | H39: Ready for Production | I39: Md Mashiul Azam Chowdhury | J39: Fariha Jabin | K39: 9/22/2025 | L39: 11/18/2025 | M39: Provide update
A40: CS-1185 | B40: Bug | C40: TSS | Create an EDLP Promotion Only Creates Error | D40: Brand | E40: Trade Spend Sandbox | F40: Unspec | G40: High | H40: Backlog | I40: Md Mashiul Azam Chowdhury | J40: Constance Wolfe | K40: 10/1/2025 | L40: 11/10/2025 | M40: Fixed?
A41: CS-1186 | B41: Bug | C41: TSS | Duplicating a Promotion Issue- Comments are not included in the copy | D41: Brand | E41: Trade Spend Sandbox | F41: Unspec | G41: High | H41: Ready for Production | I41: Bijoy Chandra Nath | J41: Constance Wolfe | K41: 10/2/2025 | L41: 11/10/2025 | M41: Provide Update
A42: CS-1187 | B42: Bug | C42: Trade Spend Sandbox | Ad Fees Step 4 Issue| If multiple events are selected the Ad Fee is split among all items in all events | D42: Brand | E42: Trade Spend Sandbox | F42: Unspec | G42: High | H42: Backlog | I42: Md Mashiul Azam Chowdhury | J42: Constance Wolfe | K42: 10/4/2025 | L42: 11/10/2025 | M42: Q1
A43: CS-1192 | B43: Bug | C43: bugs relates to EDLP | D43: Brand | E43: Trade Spend Sandbox | F43: Unspec | G43: High | H43: In Staging | I43: Md Mashiul Azam Chowdhury | J43: Fariha Jabin | K43: 10/20/2025 | L43: 11/17/2025 | M43: Provide update
A44: CS-1193 | B44: Task | C44: TSS>Step 4> Multiple Edit Divide Ad Fees by Product for Each Event Separately | D44: Brand | E44: Trade Spend Sandbox | F44: Unspec | G44: High | H44: Backlog | I44: Md Mashiul Azam Chowdhury | J44: Constance Wolfe | K44: 10/20/2025 | L44: 10/20/2025 | M44: Q1
A45: CS-1236 | B45: Bug | C45: TSS- New bugs | D45: Brand | E45: Trade Spend Sandbox | F45: Unspec | G45: High | H45: Backlog | I45: Bijoy Chandra Nath | J45: Fariha Jabin | K45: 11/27/2025 | L45: 12/9/2025 | M45: Complete?
A46: CS-1244 | B46: Bug | C46: TSS Details Page: Pricing, Allowance, Total Spend, Alert UI, and TPR Fee Calculation Issues | D46: Brand | E46: Trade Spend Sandbox | F46: Unspec | G46: High | H46: Backlog | I46: Bijoy Chandra Nath | J46: Fariha Jabin | K46: 12/24/2025 | L46: 12/24/2025 | M46: Q1
... A48: CS-1258 | B48: Bug | C48: TSS  View & Edit Promo: Multiple clicks on date edit cause application error | D48: Brand | E48: Trade Spend Sandbox | F48: Unspec | G48: High | H48: Backlog | I48: Md Mashiul Azam Chowdhury | J48: Fariha Jabin | K48: 1/21/2026 | L48: 1/21/2026 | M48: Q2
A49: CS-1259 | B49: Bug | C49: TSS > Change Message for pushing a promotion to Approved > Currently says push to trade spend | D49: Brand | E49: Trade Spend Sandbox | F49: Unspec | G49: High | H49: Backlog | M49: Q2
A50: CS-1273 | C50: TSS> View & Edit Promo Events Details > If product status changes in Retail CRM > Should the date in the Event Details Reflect the date. See decription | D50: Brand | E50: Trade Spend Sandbox | F50: Unspec | G50: High | H50: Backlog | I50: Bijoy Chandra Nath | J50: Constance Wolfe | K50: 3/26/2026 | L50: 4/23/2026
A51: CS-1353 | C51: TSS | Add 3 new Columns to Event Summary | D51: Brand | E51: Trade Spend Sandbox | F51: Unspec | G51: High | H51: In Progress | I51: Md Mashiul Azam Chowdhury Efti | J51: Constance Wolfe | K51: 4/24/2026 | L51: 4/28/2026
A52: CS-1413 | C52: TSS | Promotion Fee Value Column show 0 Value if not Filtered | D52: Brand | E52: Trade Spend Sandbox | F52: Unspec | G52: High | H52: Backlog | I52: Md Mashiul Azam Chowdhury Efti | J52: Constance Wolfe | K52: 5/23/2026 | L52: 5/23/2026
A53: CS-1414 | C53: TSS Promo Fee | Needs a Edit Option | D53: Brand | E53: Trade Spend Sandbox | F53: Unspec | G53: High | H53: Backlog | I53: Md Mashiul Azam Chowdhury Efti | J53: Constance Wolfe | K53: 5/23/2026 | L53: 5/23/2026
A54: CS-653 | B54: Task | C54: Caboodle Broker | Trade Spend Sandbox should report to Promotional Management (not Promo Planning) | D54: Brand | E54: Trade Spend Sandbox | F54: Unspec | G54: High | H54: Ready for Production | I54: Bijoy Chandra Nath | J54: Constance Wolfe | K54: 11/26/2024 | L54: 11/6/2025 | M54: Provide update
A55: CS-1196 | B55: Task | C55: TSS>Add Coupon Option> | D55: Brand | E55: Trade Spend Sandbox | F55: Unspec | G55: Medium | H55: Backlog | I55: Md Mashiul Azam Chowdhury | J55: Constance Wolfe | K55: 10/21/2025 | L55: 10/21/2025 | M55: Q2
A56: CS-1197 | B56: Task | C56: TSS> Add Sku to existing event > Allow user to choose multiple events | D56: Brand | E56: Trade Spend Sandbox | F56: Unspec | G56: Medium | H56: Backlog | I56: Md Mashiul Azam Chowdhury | J56: Constance Wolfe | K56: 10/22/2025 | L56: 10/27/2025 | M56: Q2
A57: CS-1201 | B57: Task | C57: Fix filter so User only see the Retailers they manage, the TSS & BAP Promotions they create and the Promotions on the Calendar | D57: Brand | E57: Trade Spend Sandbox | F57: Unspec | G57: Medium | H57: Backlog | I57: Md Mashiul Azam Chowdhury | J57: Constance Wolfe | K57: 10/27/2025 | L57: 11/10/2025 | M57: Moved to Admin
A58: CS-1351 | C58: TSS | Can Brands or Admin Adjust the Budget Threshold that turns the graph red if a Trade Spend % is Above 15% | D58: Brand | E58: Trade Spend Sandbox | F58: Unspec | G58: Medium | H58: Backlog | I58: Md Mashiul Azam Chowdhury Efti | J58: Constance Wolfe | K58: 4/22/2026 | L58: 4/22/2026
A59: CS-1354 | C59: TSS | Discussion for providing Actual Lift (Placeholder Ticket) | D59: Brand | E59: Trade Spend Sandbox | F59: Unspec | G59: Medium | H59: Backlog | I59: Md Mashiul Azam Chowdhury Efti | J59: Constance Wolfe | K59: 4/24/2026 | L59: 4/24/2026
A60: CS-1132 | B60: Bug | C60: When clicking the Add New Event button, the modal shows a visual glitch. | D60: Brand | E60: Trade Spend Sandbox | F60: Unspec | G60: Low | H60: Backlog | I60: Md Mashiul Azam Chowdhury | J60: Fariha Jabin | K60: 8/25/2025 | L60: 10/20/2025 | M60: Complete?
A61: CS-1178 | B61: Task | C61: EDLP events look the same as other events; there should be a different color, tag, or indicator to easily identify EDLP events. | D61: Brand | E61: Trade Spend Sandbox | F61: Unspec | G61: Low | H61: Backlog | I61: Md Mashiul Azam Chowdhury | J61: Fariha Jabin | K61: 9/22/2025 | L61: 10/20/2025 | M61: Q2
A62: CS-1372 | C62: TSS - Everyday Allowance Field Displays 0 Despite Having Value | D62: Brand | E62: Trade Spend Sandbox | F62: Unspec | G62: Low | H62: Backlog | I62: Bijoy Chandra Nath | J62: Fariha Jabin | K62: 5/4/2026 | L62: 5/4/2026
A63: CS-1381 | C63: TSS: Stores Field Accepts Negative Values in Add SKU Modal | D63: Brand | E63: Trade Spend Sandbox | F63: Unspec | G63: Low | H63: Backlog | I63: Md Mashiul Azam Chowdhury Efti | J63: Fariha Jabin | K63: 5/11/2026 | L63: 5/11/2026
A64: CS-1382 | C64: TSS ? Promotion Fees ? Products from Other Banners Are Displayed in Add Promotion Fee Modal | D64: Brand | E64: Trade Spend Sandbox | F64: Unspec | G64: Low | H64: Backlog | I64: Md Mashiul Azam Chowdhury Efti | J64: Fariha Jabin | K64: 5/11/2026 | L64: 5/11/2026
A65: CS-1436 | B65: Task | C65: TSS | EDLP Promotional Reporting only Populating the Month of January | D65: Brand | E65: TSS/Reports | G65: Highest | H65: Backlog | I65: Md Mashiul Azam Chowdhury Efti | J65: Constance Wolfe | K65: 46211.037 | L65: 46211.037
A66: CS-532 | B66: Task | C66: Trade Spend | Promo Event Details | Is it possible to add a sku without going thru the stepper again? | D66: Brand | E66: Trade Spend Sandbox | F66: Unspec | G66: Low | H66: Backlog | J66: Constance Wolfe | K66: 5/28/2024 | L66: 5/28/2024 | M66: Complete?
A67: ▸ Promotional Calendar (1)
A68: CS-1202 | B68: Task | C68: Promotional Calendar: If Event stretches across more than 1 month, show it on all months that are included | D68: Brand | E68: Promotional Calendar | F68: Unspec | G68: Medium | H68: Backlog | I68: Md Mashiul Azam Chowdhury | J68: Constance Wolfe | K68: 10/27/2025 | L68: 10/27/2025 | M68: Q1 or Q2
A69: HOME PAGE
A70: CS-1307 | C70: Home Page Banner Report > Add Scroll option | D70: Broker Dashboard | E70: Market Overview | F70: Unspec | G70: High | H70: Backlog | I70: Md Mashiul Azam Chowdhury Efti | J70: Constance Wolfe | K70: 3/31/2026 | L70: 3/31/2026
A71: Need
C72: SUMMARY | D72: Area
B73: Added 7/27/26 | C73: BRAND DASHBOARD | D73: Brand Dashboard
C74: Update Brand Dashboard Similar to Broker Dashboard | D74: Brand Dashboard
C75: Include Ask Caboodle | D75: Brand Dashboard | F75: Created by Efti Spring 2026
C76: See mock up from Efti from Spring 2026 (Screenshot to the right) | D76: Brand Dashboard
C77: Flags alerting user of upcoming Task, promotional submission, category Review Deadlines
C78: PIPELINE
A79: Added Ticket 1425 | C79: Allow User to Hide or Archive Plans | D79: Pipeline
C80: Label The Plans Project | D80: Pipeline
C81: Allow User to Hide Complete Tasks (Check Box) | D81: Pipeline
C82: Allow User to enter Due Date | D82: Pipeline
C83: Create Calendar View for Deadlines | D83: Pipeline
A84: BMP1 | B84: NEW 7/20 | C84: Allow User to assign to Users (It adds email but not assignments) | D84: Pipelione
A85: BMP2 | C85: Option to not send email for every update (currently everytime there is an update it sends an email to everyone, even if it's just an edit. For example if users simply corrects a spelling and hits save, it sends an email to everyone assigned to the task. When the other users get the email, it's not clear why they are getting an update, it appears nothing has changed. | D85: Pipeline
C86: RETAIL REPORT
C87: Display Dashboard Summary see this link https://lovable.dev/projects/8385ee0b-effd-4a8f-8cb9-27477a3fccfc | D87: Retailers
C88: TSS
A89: BMTSS1 | B89: NEW 7/20 | C89: Remove or Modify Approved Promotions
A90: BMTSS2 | C90: Currently there is no option to remove a promotion from Approved Promotions, once it’s approved. The current work around is to delete the promotion that was Approved from the Sandbox. The SOP is to create a copy of the Approved Promotion in the Sandbox and add this to the name of the Promotion "Original Version” Date, User Initial’. Then the original version is deleted. Modifying Approved Promotions If the User wants to make any changes to the Approved Promotion, the user creates a copy of the Original Version, then edits the name to reflect “Revised, Date, Users Initials” Then modifications to the this version of the Sandbox are made, then pushed to Approved. This is to preserve all versions of the promotion if changes are made.
A91: BMTSS3 | B91: New 7/29 | C91: EDLP in Stepper needs some clarification. Currently a user can enter an EDLP in the stepper. They can also add it in the Trade Spend Results page in the Edit promo details section. We need to clarify when it should be used in the stepper and when it should be used in the edit promo details. NOTE: it may depend on if the user is trying to enter both an EDLP and temporary price reductions...vs. just an EDLP | D91: TSS
C92: Question: Promotional Year: User Needs Clarification for if it's important to set the year in the TSS before starting a promotion. For example it's 2026 now but I want to build a promotion for 2027, Does the user need to change the year on the main page or can they start in the year of 2026 and ener 2027 dates when they build the promotion? See Screen shots to the right
A93: BMTSS4 | C93: Actualize Promotions: What is best method to actualize promotions? Currently we advise users to make a copy of the original promotion and enter the actuals from an external data sourse. However the Data source is in the system, so is there a way to automate this process? We should also have some reports aroud plan to actual | D93: TSS
A94: BMTSS5 | B94: 46232 | C94: EDIT PROMO DETAILS User needs a little more space at the bottom of Promo event details if only 1 row is showing. See Screenshot to the right | D94: TSS
A95: BMTSS6 | C95: EDLP is showing up in the Promotional Calendar only in the month of Jan. It should be across all months. It's working correctly in Broker Promotional Management. It might be because it's still pulling from the TSS not Approved? Same is happening in the Monthly Report | D95: TSS/Promo Calendar
B96: NEW 7/20 | C96: PRODUCT SPEC
A97: BMTPS1 | C97: Add Product UPC to Pricing Module | D97: Product Specs
C98: RETAILER CRM
A99: BMTRC1 | C99: Add store level listing from Banner Page. It could be a link to a new page within Caboodle. See the STORE REPORT MGMT Tab | D99: CRM
C114: Important findings before writing — data/jira-tickets shows strong overlap:
C115: BMTSS3 (EDLP stepper vs edit details) → directly matches CS-1302 ("determine if this should be added in the Promo Results Page … or Step 4 Metrics in the stepper").
C116: BMTSS4 (Actualize) → there's already a working file CS-NEW-brand-tss-actualize-promotions.md in tickets/trade-spend/, plus Jira CS-1280 (Actuals Auto Updated from Distributor Reports), CS-1283, CS-1335.
...

Sheet STORE REPORT MGMT 
A2: Concept: Many Brands have a direct to store program for smaller stores. They need a way to keep track of orders and communications.
A3: Proposed Caboodle Solution: Upload brand Store list into a separate Distributor report but very similar to the current one. Call it "House Accounts" (NOTE: I've been wanting to utilize the old UNFI & KeHE reports for agnotic reporting anyway so this may be a good solution)
A5: See Distributor Reports> Sales Details where store names, addresses and order details are provided via uplaod
A6: The void report could be converted to stores instead of warehouses so user can viscualize gaps in orders
A7: Install a email automation & Trigger API that allows users to build trigger logic for emails. For example 30-day inactivity…or lifecycle automation
A8: Need to think about email templates, I don't know that we want to get into template builders but maybe we utilize claude design? Or they could simply copy & paste a design into an editor?
A10: These 2 charts are for inspiration > It outlines how we already ingest and report very similar data
A38: SRM1

Sheet Reports
A1: Reports — 41 tickets
A3: Issue Key | B3: Type | C3: Summary | D3: Area | E3: Caboodle Module | F3: FE/BE | G3: Priority | H3: Status | I3: Assignee | J3: Reporter | K3: Created | L3: Updated | M3: Due / Note
A4: ▸ Broker Market Activities (1)
A5: CS-1203 | B5: Bug | C5: Reports>Broker Market Activity Report throws Error | D5: Reports | E5: Broker Market Activities | F5: Unspec | G5: Highest | H5: Backlog | I5: Md Mashiul Azam Chowdhury | J5: Constance Wolfe | K5: 10/28/2025 | L5: 11/10/2025 | M5: ??
A6: ▸ Category Review Report (2)
A7: CS-1149 | B7: Bug | C7: Reports | Category Review Uploads & Data Pushes | D7: Reports | E7: Category Review Report | F7: Unspec | G7: High | H7: Backlog | I7: Bijoy Chandra Nath | J7: Constance Wolfe | K7: 8/29/2025 | L7: 11/10/2025 | M7: STORY 1329
A8: CS-1291 | C8: Reports | Category Review when Reviews are uploaded in Brand Environment It's pushing to all Brands | D8: Reports | E8: Category Review Report | F8: Unspec | G8: Medium | H8: Backlog | I8: Bijoy Chandra Nath | J8: Constance Wolfe | K8: 3/31/2026 | L8: 5/4/2026 | M8: STORY 1329
A9: ▸ Retail Reports (4)
A10: CS-1204 | B10: Bug | C10: Reports > Retail Report Activities Filter Doesn't Work | D10: Reports | E10: Retail Reports | F10: Unspec | G10: Highest | H10: Backlog | I10: Md Mashiul Azam Chowdhury | J10: Constance Wolfe | K10: 10/28/2025 | L10: 11/10/2025 | M10: Q1
A11: CS-1162 | B11: Task | C11: [FE] Store Insight whole report delete by filter | D11: Reports | E11: Retail Reports | F11: FE | G11: High | H11: Reopened | I11: Md Mashiul Azam Chowdhury | J11: Md Mashiul Azam Chowdhury | K11: 9/10/2025 | L11: 11/6/2025
A12: CS-1297 | C12: New Report | Retail Portal Data Upload | D12: Reports | E12: Retail Reports | F12: Unspec | G12: High | H12: Backlog | I12: Md Mashiul Azam Chowdhury Efti | J12: Constance Wolfe | K12: 3/31/2026 | L12: 3/31/2026
A13: CS-1347 | C13: Banner List Not Sorted in Ascending Order in Retail Report > Products | D13: Reports | E13: Retail Reports | F13: Unspec | G13: Medium | H13: Backlog | I13: Bijoy Chandra Nath | J13: Taslima Akbar Keya | K13: 4/21/2026 | L13: 4/21/2026
A14: ▸ Sales Tracker (1)
A15: CS-1306 | C15: Report | Sales Tracking for Prospects | D15: Reports | E15: Sales Tracker | F15: Unspec | G15: High | H15: Backlog | I15: Md Mashiul Azam Chowdhury Efti | J15: Constance Wolfe | K15: 3/31/2026 | L15: 6/23/2026
A16: ▸ Trade Spend Rollup (5)
A17: CS-1190 | B17: Task | C17: Trade Spend Roll Up Report | Add Column for Total Trade Spend that Adds the TPR Spend w/ Ad/TPR Fees | D17: Reports | E17: Trade Spend Rollup | F17: Unspec | G17: Highest | H17: Backlog | I17: Md Mashiul Azam Chowdhury | J17: Constance Wolfe | K17: 10/11/2025 | L17: 10/11/2025 | M17: Q2
A18: CS-1339 | C18: Enhance Trade Spend Rollup Report with Hyperlinks and Spend Totals | D18: Reports | E18: Trade Spend Rollup | F18: Unspec | G18: Highest | H18: Reopened | I18: Md Mashiul Azam Chowdhury Efti | J18: Md Mashiul Azam Chowdhury Efti | K18: 4/7/2026 | L18: 5/5/2026
A19: CS-1375 | C19: [BE] Trade Spend Roll Up Report | Add Column for Total Trade Spend that Adds the TPR Spend w/ Ad/TPR Fees | D19: Reports | E19: Trade Spend Rollup | F19: BE | G19: Highest | H19: Backlog | I19: Bijoy Chandra Nath | J19: Md Mashiul Azam Chowdhury Efti | K19: 5/5/2026 | L19: 5/5/2026
A20: CS-1230 | B20: Task | C20: Reports>Trade Spend Roll Up > Updates on Headers (Net to Gross) + other Minor Changes | D20: Reports | E20: Trade Spend Rollup | F20: Unspec | G20: High | H20: Backlog | I20: Md Mashiul Azam Chowdhury | J20: Constance Wolfe | K20: 11/17/2025 | L20: 11/17/2025 | M20: Still some items to complete
A21: CS-1246 | B21: Task | C21: [BE] Add Gross Unit Calculation in Roll up report | D21: Reports | E21: Trade Spend Rollup | F21: BE | G21: High | H21: In Progress | I21: Bijoy Chandra Nath | J21: Bijoy Chandra Nath | K21: 12/24/2025 | L21: 12/24/2025 | M21: ??
A22: ▸ Monthly Report (7)
A23: CS-1335 | C23: Fix Monthly Report Calculations and Data Refresh Issues | D23: Reports | E23: Monthly Report | F23: Unspec | G23: Highest | H23: Backlog | I23: Bijoy Chandra Nath | J23: Md Mashiul Azam Chowdhury Efti | K23: 4/7/2026 | L23: 5/4/2026
A24: CS-1336 | C24: Improve Monthly Report Layout, Filtering and Navigation | D24: Reports | E24: Monthly Report | F24: Unspec | G24: Highest | H24: Backlog | I24: Bijoy Chandra Nath | J24: Md Mashiul Azam Chowdhury Efti | K24: 4/7/2026 | L24: 5/12/2026
A25: CS-1283 | C25: Monthly Report | Importing Actuals (Manually and Automated) | D25: Reports | E25: Monthly Report | F25: Unspec | G25: High | H25: Ready for Production | I25: Bijoy Chandra Nath | J25: Constance Wolfe | K25: 3/31/2026 | L25: 5/21/2026
A26: CS-1285 | C26: Monthly Report | Need Category in Filter w/ Dependancy for Products | D26: Reports | E26: Monthly Report | F26: Unspec | G26: High | H26: In Progress | I26: Bijoy Chandra Nath | J26: Constance Wolfe | K26: 3/31/2026 | L26: 5/5/2026
A27: CS-1352 | C27: Monthly Report | YOY Report Needs Date Selection Option | D27: Reports | E27: Monthly Report | F27: Unspec | G27: High | H27: Backlog | I27: Bijoy Chandra Nath | J27: Constance Wolfe | K27: 4/24/2026 | L27: 5/11/2026
A28: CS-1388 | C28: Monthly Report | Add Month to Filter | D28: Reports | E28: Monthly Report | F28: Unspec | G28: Low | H28: Backlog | I28: Md Mashiul Azam Chowdhury Efti | J28: Constance Wolfe | K28: 5/12/2026 | L28: 5/14/2026
A29: CS-1431 | B29: Bug | C29: Monthly Report | Import Actuals > Failed Records Reason seem invalid | D29: Brand | E29: Monthly Report | G29: Highest | H29: Backlog | I29: Bijoy Chandra Nath | J29: Constance Wolfe | K29: 46210.061 | L29: 46210.46
A30: CS-1405 | C30: [BE] Monthly Report | Add Month to Filter | D30: Reports | E30: Monthly Report | F30: BE | G30: Low | H30: Backlog | I30: Bijoy Chandra Nath | J30: Md Mashiul Azam Chowdhury Efti | K30: 5/14/2026 | L30: 5/14/2026
A31: ▸ SPINS (3)
A32: CS-1223 | B32: Task | C32: Remove legacy SPINS data  keep only filtered, relevant datasets. | D32: Reports | E32: SPINS | F32: Unspec | G32: High | H32: Backlog | J32: Md Mashiul Azam Chowdhury | K32: 11/6/2025 | L32: 11/6/2025 | M32: Q1
A33: CS-1293 | C33: Reports | SPINS SPINS > Prep system to accept all measures | D33: Reports | E33: SPINS | F33: Unspec | G33: High | H33: Backlog | I33: Md Mashiul Azam Chowdhury Efti | J33: Constance Wolfe | K33: 3/31/2026 | L33: 3/31/2026
A34: CS-1294 | C34: Report SPINS Updates | D34: Reports | E34: SPINS | F34: Unspec | G34: High | H34: Backlog | I34: Md Mashiul Azam Chowdhury Efti | J34: Constance Wolfe | K34: 3/31/2026 | L34: 3/31/2026
A35: ▸ Distributor Report (16)
A36: CS-1333 | C36: Fix Distributor Report Calculations and Data Consistency | D36: Reports | E36: Distributor Report | F36: Unspec | G36: Highest | H36: Backlog | I36: Bijoy Chandra Nath | J36: Md Mashiul Azam Chowdhury Efti | K36: 4/7/2026 | L36: 5/16/2026
A37: CS-1421 | C37: Distributor Report | Velocity Calculations Need Review | D37: Reports | E37: Distributor Report | F37: Unspec | G37: Highest | H37: Backlog | I37: Md Mashiul Azam Chowdhury Efti | J37: Constance Wolfe | K37: 6/17/2026 | L37: 6/20/2026
A38: CS-1422 | C38: Product Specs & Distributor Report KEHE Master Pack Issue | D38: Reports | E38: Distributor Report | F38: Unspec | G38: Highest | H38: Backlog | I38: Md Mashiul Azam Chowdhury Efti | J38: Constance Wolfe | K38: 6/17/2026 | L38: 6/20/2026
A39: CS-1222 | B39: Task | C39: Build and validate the Single Distributor Report. | D39: Reports | E39: Distributor Report | F39: Unspec | G39: High | H39: In Progress | J39: Md Mashiul Azam Chowdhury | K39: 11/6/2025 | L39: 11/6/2025 | M39: In Progress
A40: CS-1256 | B40: Task | C40: New Filter For Distributor Report | D40: Reports | E40: Distributor Report | F40: Unspec | G40: High | H40: Backlog | I40: Md Mashiul Azam Chowdhury | J40: Constance Wolfe | K40: 1/10/2026 | L40: 1/10/2026 | M40: Q1
A41: CS-1275 | C41: Distributor Report | UNFI Continue testing the crawler service to ensure it can handle website changes | D41: Reports | E41: Distributor Report | F41: Unspec | G41: High | H41: Backlog | I41: Bijoy Chandra Nath | J41: Constance Wolfe | K41: 3/31/2026 | L41: 5/4/2026
A42: CS-1278 | C42: Distributor Report | Should we be able to do manual uploads? | D42: Reports | E42: Distributor Report | F42: Unspec | G42: High | H42: In Staging | I42: Bijoy Chandra Nath | J42: Constance Wolfe | K42: 3/31/2026 | L42: 5/13/2026
A43: CS-1279 | C43: Distributor Report Discussion | Auto Update Retailer CRM Item Status (From NA/Pending) to Active | D43: Reports | E43: Distributor Report | F43: Unspec | G43: High | H43: Backlog | I43: Bijoy Chandra Nath | J43: Constance Wolfe | K43: 3/31/2026 | L43: 5/11/2026
A44: CS-1281 | C44: Distributor Report | Auto Flags for New and Disco Items/Retailers (Summary of update x new x disco) | D44: Reports | E44: Distributor Report | F44: Unspec | G44: High | H44: Backlog | I44: Bijoy Chandra Nath | J44: Constance Wolfe | K44: 3/31/2026 | L44: 5/13/2026
A45: CS-1286 | C45: Distributor Report | Reorganize Filter | D45: Reports | E45: Distributor Report | F45: Unspec | G45: High | H45: In Progress | I45: Md Mashiul Azam Chowdhury Efti | J45: Constance Wolfe | K45: 3/31/2026 | L45: 5/7/2026
A46: CS-1312 | C46: Distributor Report | Adjust UNFI Sales Dollars Calculations to match Distributor MOD pricing in Caboodle | D46: Reports | E46: Distributor Report | F46: Unspec | G46: High | H46: In Progress | I46: Bijoy Chandra Nath | J46: Constance Wolfe | K46: 4/2/2026 | L46: 5/11/2026 | M46: Add Message to User about Sale Dollar from UNFI VS KeHE
A47: CS-1334 | C47: Improve Distributor Report Filtering, Naming and Export | D47: Reports | E47: Distributor Report | F47: Unspec | G47: High | H47: Backlog | I47: Md Mashiul Azam Chowdhury Efti | J47: Md Mashiul Azam Chowdhury Efti | K47: 4/7/2026 | L47: 5/4/2026 | M47: STORY
A48: CS-1387 | C48: Admin | Data Sync Not working > Not Populating Distributor Report | D48: Reports | E48: Distributor Report | F48: Unspec | G48: High | H48: Backlog | I48: Md Mashiul Azam Chowdhury Efti | J48: Constance Wolfe | K48: 5/12/2026 | L48: 5/12/2026
A49: CS-1402 | C49: [FE] Distributor Sales Report | Import functionality | D49: Reports | E49: Distributor Report | F49: FE | G49: High | H49: In Staging | I49: Md Mashiul Azam Chowdhury Efti | J49: Md Mashiul Azam Chowdhury Efti | K49: 5/13/2026 | L49: 5/13/2026
A50: CS-1276 | C50: Current UNFI & KeHE Reports > Determine if we should use them generically | D50: Reports | E50: Distributor Report | F50: Unspec | G50: Medium | H50: Backlog | I50: Md Mashiul Azam Chowdhury Efti | J50: Constance Wolfe | K50: 3/31/2026 | L50: 3/31/2026
A51: CS-1426 | B51: Bug | C51: Distributor Report | POD Calculation is incorrect | D51: Brand | E51: Distributor Report | G51: Highest | H51: Backlog | I51: Bijoy Chandra Nath | J51: Constance Wolfe | K51: 46203.838 | L51: 46204.413
A52: CS-1433 | B52: Bug | C52: Distributor Report | Pulling in Prior Year Sales | It sould only pull in Current Year Sales | D52: Brand | E52: Distributor Report | G52: High | H52: Backlog | I52: Md Mashiul Azam Chowdhury Efti | J52: Constance Wolfe | K52: 46210.982 | L52: 46210.982
A53: CS-1407 | C53: Distributor Report | Update DC Cases Sold Report CSV File Name | D53: Reports | E53: Distributor Report | F53: Unspec | G53: Low | H53: Backlog | I53: Md Mashiul Azam Chowdhury Efti | J53: Taslima Akbar Keya | K53: 5/20/2026 | L53: 5/20/2026
A54: ▸ Banner-to-DC (New Report) (1)
A55: CS-1295 | C55: New Report | Banner to DC Reporting | D55: Reports | E55: Banner-to-DC (New Report) | F55: Unspec | G55: High | H55: Backlog | I55: Md Mashiul Azam Chowdhury Efti | J55: Constance Wolfe | K55: 3/31/2026 | L55: 6/23/2026
A56: ▸ Reports (Unspecified) (1)
A57: CS-1032 | B57: Task | C57: [BE] Reports > Promoted Case Allowance -Please start | D57: Reports | E57: Reports (Unspecified) | F57: BE | G57: High | H57: In Progress | I57: Bijoy Chandra Nath | J57: Constance Wolfe | K57: 7/1/2025 | L57: 9/25/2025 | M57: Q1
A58: Need
C59: SUMMARY | D59: Area
C60: DISTRIBUTOR REPORT | E60: Date Added
B61: RDR1 | C61: Should user be able to Export the Data? | D61: Brand Distributor Report
B62: RDR2 | C62: Only report a rolling latest 12 months unless filtered differently | D62: Brand Distributor Report | E62: 46210
C63: BROKER MARKET OVERVIEW
B64: RBMO1 | C64: Sort Function: There is a Date Time but it does't work. There should be a date on this list | D64: Brand Broker Market Overiew
B65: RBMO2 | C65: Needs Summary Report See Prototype | D65: https://lovable.dev/projects/8385ee0b-effd-4a8f-8cb9-27477a3fccfc
C66: SPINS
B67: RBS1 | C67: Hide Market Insights | D67: SPINS
C68: SALES TRACKER | D68: Sales Tracker
B69: RBST1 | C69: After clicking a retailer in a region to view the product details, there is a back button. When the user clicks the back button, it takes them to the international region no matter what region they started in. | D69: Sales Tracker
B70: New 7/20 | C70: Sales Tracker Needs a new look: See loveable link for inspiration | D70: Sales Tracker | E70: https://lovable.dev/projects/8385ee0b-effd-4a8f-8cb9-27477a3fccfc

Sheet Admin
A1: Admin — 67 tickets
A3: Issue Key | B3: Type | C3: Summary | D3: Area | E3: Caboodle Module | F3: FE/BE | G3: Priority | H3: Status | I3: Assignee | J3: Reporter | K3: Created | L3: Updated | M3: Due / Note
A4: ▸ CRM Data Upload (11)
A5: CS-1308 | C5: Admin >CRM Data Upload > Stores > Edit Store Name failure | D5: Admin | E5: CRM Data Upload | F5: Unspec | G5: Highest | H5: Backlog | I5: Md Mashiul Azam Chowdhury Efti | J5: Constance Wolfe | K5: 3/31/2026 | L5: 3/31/2026
A6: CS-1309 | C6: Admin CRM Data Upload>Stores > Can we add Delete Button | D6: Admin | E6: CRM Data Upload | F6: Unspec | G6: High | H6: Backlog | I6: Md Mashiul Azam Chowdhury Efti | J6: Constance Wolfe | K6: 3/31/2026 | L6: 3/31/2026
A7: CS-1342 | C7: Admin | CRM Data Upload > Stores Upload Issue | D7: Admin | E7: CRM Data Upload | F7: Unspec | G7: High | H7: Backlog | I7: Bijoy Chandra Nath | J7: Constance Wolfe | K7: 4/10/2026 | L7: 5/4/2026
A8: CS-1384 | C8: Admin Banner Sku Upload Failed Records | Please Review errors: The provided banner name doesn't match any existing Caboodle System banners | D8: Admin | E8: CRM Data Upload | F8: Unspec | G8: High | H8: Backlog | I8: Bijoy Chandra Nath | J8: Constance Wolfe | K8: 5/11/2026 | L8: 5/12/2026
A9: CS-1419 | C9: Admin CRM Data Upload Stores | Remove Duplicates & Resolve Multi-Mapping | D9: Admin | E9: CRM Data Upload | F9: Unspec | G9: High | H9: Backlog | I9: Md Mashiul Azam Chowdhury Efti | J9: Constance Wolfe | K9: 6/5/2026 | L9: 6/5/2026
A10: CS-496 | B10: Bug | C10: Banner Upload Error Messaging | D10: Admin | E10: CRM Data Upload | F10: Unspec | G10: High | H10: Backlog | J10: Constance Wolfe | K10: 5/2/2024 | L10: 11/10/2025 | M10: ??
A11: CS-1364 | C11: CRM Data Upload | Error Occurs When Updating Store from Stores Section | D11: Admin | E11: CRM Data Upload | F11: Unspec | G11: Medium | H11: Backlog | I11: Md Mashiul Azam Chowdhury Efti | J11: Taslima Akbar Keya | K11: 4/30/2026 | L11: 4/30/2026
A12: CS-1037 | B12: Bug | C12: [BE] No error message when uploading a blank file | D12: Admin | E12: CRM Data Upload | F12: BE | G12: Low | H12: Backlog | I12: Bijoy Chandra Nath | J12: Fariha Jabin | K12: 7/1/2025 | L12: 11/10/2025 | M12: Q1
A13: CS-1042 | B13: Bug | C13: banner edit modal  sometimes retailer name shows retailer id | D13: Admin | E13: CRM Data Upload | F13: Unspec | G13: Low | H13: Reopened | I13: Md Mashiul Azam Chowdhury | J13: Fariha Jabin | K13: 7/1/2025 | L13: 11/17/2025
A14: CS-1292 | C14: Data Uploads | Implement Dynamic Data Uploads to support formats that don't match templates (Import Wizard) | D14: Admin | E14: CRM Data Upload | F14: Unspec | G14: Low | H14: Backlog | I14: Md Mashiul Azam Chowdhury Efti | J14: Constance Wolfe | K14: 3/31/2026 | L14: 3/31/2026
A15: CS-1365 | C15: CRM Data Upload | Regions List UI Not Properly Formatted in Retailers Section | D15: Admin | E15: CRM Data Upload | F15: Unspec | G15: Low | H15: Backlog | J15: Taslima Akbar Keya | K15: 4/30/2026 | L15: 4/30/2026
A16: ▸ Data Mapping (19)
A17: CS-1266 | C17: [BE] Data Mapping > Unmapped Filter Needs Options for all Properties | D17: Admin | E17: Data Mapping | F17: BE | G17: Highest | H17: Reopened | I17: Bijoy Chandra Nath | J17: Constance Wolfe | K17: 3/24/2026 | L17: 5/24/2026
A18: CS-1268 | C18: [BE] Data Mapping > Allow user to change status (any) in unmapped data | D18: Admin | E18: Data Mapping | F18: BE | G18: Highest | H18: Ready for Production | I18: Bijoy Chandra Nath | J18: Constance Wolfe | K18: 3/24/2026 | L18: 5/21/2026
A19: CS-1331 | C19: Enhance Data Mapping Module Usability and Filtering | D19: Admin | E19: Data Mapping | F19: Unspec | G19: Highest | H19: Backlog | I19: Md Mashiul Azam Chowdhury Efti | J19: Md Mashiul Azam Chowdhury Efti | K19: 4/7/2026 | L19: 5/4/2026
A20: CS-1415 | C20: Data Mapping | Unmapped Store List | D20: Admin | E20: Data Mapping | F20: Unspec | G20: Highest | H20: Backlog | I20: Bijoy Chandra Nath | J20: Constance Wolfe | K20: 5/26/2026 | L20: 6/1/2026
A21: CS-1416 | C21: Data Mapping Filter Issue | D21: Admin | E21: Data Mapping | F21: Unspec | G21: Highest | H21: Backlog | I21: Bijoy Chandra Nath | J21: Constance Wolfe | K21: 5/27/2026 | L21: 6/1/2026
A22: CS-1214 | B22: Task | C22: Implement and test Crisp integration Or Data Scrapping (API connection, data sync). | D22: Admin | E22: Data Mapping | F22: Unspec | G22: High | H22: In Progress | I22: Bijoy Chandra Nath | J22: Md Mashiul Azam Chowdhury | K22: 11/6/2025 | L22: 11/24/2025
A23: CS-1216 | B23: Task | C23: Data Mapping Expansion  Phase 2 | D23: Admin | E23: Data Mapping | F23: Unspec | G23: High | H23: In Progress | J23: Md Mashiul Azam Chowdhury | K23: 11/6/2025 | L23: 12/1/2025
A24: CS-1219 | B24: Task | C24: Integrate with the Data Mapping module to ensure mapped fields align during import/export. | D24: Admin | E24: Data Mapping | F24: Unspec | G24: High | H24: In Progress | J24: Md Mashiul Azam Chowdhury | K24: 11/6/2025 | L24: 11/6/2025 | M24: Complete?
A25: CS-1343 | C25: [BE] Data Mapping | Re-Resolve Not Working | D25: Admin | E25: Data Mapping | F25: BE | G25: High | H25: Ready for Production | I25: Bijoy Chandra Nath | J25: Constance Wolfe | K25: 4/10/2026 | L25: 5/21/2026
A26: CS-1389 | C26: Data Mapping | Remove old Brand Data | D26: Admin | E26: Data Mapping | F26: Unspec | G26: High | H26: Backlog | I26: Md Mashiul Azam Chowdhury Efti | J26: Constance Wolfe | K26: 5/12/2026 | L26: 5/12/2026
A27: CS-1390 | C27: Admin | Data Mapping | New Bot Implementation for Broker Brands | D27: Admin | E27: Data Mapping | F27: Unspec | G27: High | H27: Backlog | I27: Md Mashiul Azam Chowdhury Efti | J27: Constance Wolfe | K27: 5/12/2026 | L27: 5/12/2026
A28: CS-1391 | C28: Data Mapping | Banner Sku Upload | D28: Admin | E28: Data Mapping | F28: Unspec | G28: High | H28: Backlog | I28: Md Mashiul Azam Chowdhury Efti | J28: Constance Wolfe | K28: 5/12/2026 | L28: 5/12/2026
A29: CS-1418 | C29: Data Mapping/CRM Data Upload | Stores Add A Store Field list is missing State | D29: Admin | E29: Data Mapping | F29: Unspec | G29: High | H29: Backlog | I29: Md Mashiul Azam Chowdhury Efti | J29: Constance Wolfe | K29: 6/5/2026 | L29: 6/5/2026
A30: CS-487 | B30: Task | C30: [BE] Saving Banner SKU Failed Records and automatically adding them back into the system once we've matched up the unrecognized banners from the Data Mapping section | D30: Admin | E30: Data Mapping | F30: BE | G30: Medium | H30: Backlog | I30: Bijoy Chandra Nath | J30: Bijoy Chandra Nath | K30: 4/29/2024 | L30: 9/25/2025 | M30: ??
A31: CS-1366 | C31: Data Mapping | Mapping Status Not Immediately Updated Across Pagination in Unmapped Records | D31: Admin | E31: Data Mapping | F31: Unspec | G31: Low | H31: Backlog | I31: Md Mashiul Azam Chowdhury Efti | J31: Taslima Akbar Keya | K31: 4/30/2026 | L31: 4/30/2026
A32: CS-1409 | C32: [BE] Data Mapping | Allow user to cancel the exportation of Unmapped Records | D32: Admin | E32: Data Mapping | F32: BE | G32: Low | H32: Backlog | I32: Bijoy Chandra Nath | J32: Taslima Akbar Keya | K32: 5/21/2026 | L32: 5/21/2026
A33: CS-1410 | C33: [FE] Data Mapping | Unmapped Filter: Ordered the hierarchy of the filters based on the entity, mapping status | D33: Admin | E33: Data Mapping | F33: FE | G33: Low | H33: Backlog | I33: Md Mashiul Azam Chowdhury Efti | J33: Taslima Akbar Keya | K33: 5/21/2026 | L33: 5/21/2026
A34: CS-1411 | C34: [FE] Data Mapping | Filter : Refresh page removes the filter | D34: Admin | E34: Data Mapping | F34: FE | G34: Low | H34: Backlog | I34: Md Mashiul Azam Chowdhury Efti | J34: Taslima Akbar Keya | K34: 5/21/2026 | L34: 5/21/2026
A35: CS-1435 | B35: Task | C35: Data Mapping | Pulling in KeHE POD Current Year QTY 0 (It Should Not) | D35: Admin | E35: Data Mapping | G35: High | H35: Backlog | I35: Md Mashiul Azam Chowdhury Efti | J35: Constance Wolfe | K35: 46210.985 | L35: 46210.985
A36: CS-1412 | C36: Data Mapping | Add export and filter related some new feature | D36: Admin | E36: Data Mapping | F36: Unspec | G36: Low | H36: Backlog | I36: Md Mashiul Azam Chowdhury Efti | J36: Taslima Akbar Keya | K36: 5/21/2026 | L36: 5/25/2026
A37: ▸ User Management (17)
A38: CS-1325 | C38: Improve Broker Invitation and Brand Environment Setup | D38: Admin | E38: User Management | F38: Unspec | G38: High | H38: Backlog | I38: Bijoy Chandra Nath | J38: Md Mashiul Azam Chowdhury Efti | K38: 4/7/2026 | L38: 5/4/2026
A39: CS-1379 | C39: User Managemnet | Invitation Registration Link Redirects Logged-In Users to Login Page Instead of Signup Page | D39: Admin | E39: User Management | F39: Unspec | G39: High | H39: Backlog | I39: Md Mashiul Azam Chowdhury Efti | J39: Taslima Akbar Keya | K39: 5/10/2026 | L39: 5/12/2026
A40: CS-1290 | C40: ADMIN | Invite Broker > The Email Said it was inviting user as Sub Broker instead of Broker | D40: Admin | E40: User Management | F40: Unspec | G40: Medium | H40: Backlog | I40: Bijoy Chandra Nath | J40: Constance Wolfe | K40: 3/31/2026 | L40: 5/4/2026
A41: CS-1370 | C41: User Management | First Name Column Overlaps with Role Column on Window Resize (?80%) in User Management | D41: Admin | E41: User Management | F41: Unspec | G41: Medium | H41: Backlog | I41: Md Mashiul Azam Chowdhury Efti | J41: Taslima Akbar Keya | K41: 5/3/2026 | L41: 5/12/2026
A42: CS-1377 | C42: User Managemnet | Resend Invitation Button Does Not Send New Invitation Email | D42: Admin | E42: User Management | F42: Unspec | G42: Medium | H42: Backlog | I42: Bijoy Chandra Nath | J42: Taslima Akbar Keya | K42: 5/10/2026 | L42: 5/12/2026
A43: CS-1378 | C43: User Managemnet | Prevent Multiple Pending Invitations for the Same Brand Owner Role | D43: Admin | E43: User Management | F43: Unspec | G43: Medium | H43: Backlog | I43: Bijoy Chandra Nath | J43: Taslima Akbar Keya | K43: 5/10/2026 | L43: 5/12/2026
A44: CS-1392 | C44: User Management | User Enrollment | D44: Admin | E44: User Management | F44: Unspec | G44: Medium | H44: Backlog | I44: Md Mashiul Azam Chowdhury Efti | J44: Taslima Akbar Keya | K44: 5/12/2026 | L44: 5/12/2026
A45: CS-562 | B45: Task | C45: [BE] Implement User-Based Permission Control Module | D45: Admin | E45: User Management | F45: BE | G45: Medium | H45: In Progress | I45: Bijoy Chandra Nath | J45: Bijoy Chandra Nath | K45: 6/24/2024 | L45: 9/25/2025 | M45: Provide update
A46: CS-1078 | B46: Bug | C46: Invite User - role - brand - Select All checkbox behaves incorrectly | D46: Admin | E46: User Management | F46: Unspec | G46: Low | H46: Backlog | J46: Fariha Jabin | K46: 7/22/2025 | L46: 11/10/2025 | M46: ??
A47: CS-1376 | C47: User Managemnet | Show Proper Error Message for Cancelled Invitation Signup Attempt | D47: Admin | E47: User Management | F47: Unspec | G47: Low | H47: Backlog | I47: Bijoy Chandra Nath | J47: Taslima Akbar Keya | K47: 5/10/2026 | L47: 5/12/2026
A48: CS-1393 | C48: User Management | Invited Users List Showing Unknown as User Type | D48: Admin | E48: User Management | F48: Unspec | G48: Low | H48: Backlog | I48: Bijoy Chandra Nath | J48: Taslima Akbar Keya | K48: 5/12/2026 | L48: 5/12/2026
A49: CS-1394 | C49: User Management | Broker Invitation Email Sent as Sub-Broker Causing Invitation Acceptance Failure | D49: Admin | E49: User Management | F49: Unspec | G49: Low | H49: Backlog | I49: Bijoy Chandra Nath | J49: Taslima Akbar Keya | K49: 5/12/2026 | L49: 5/12/2026
A50: CS-1395 | C50: User Managemnet | Phone Number Field Accepts Invalid Input Without Validation | D50: Admin | E50: User Management | F50: Unspec | G50: Low | H50: Backlog | I50: Md Mashiul Azam Chowdhury Efti | J50: Taslima Akbar Keya | K50: 5/12/2026 | L50: 5/12/2026
A51: CS-1396 | C51: User Managemnet | View Brand Info Label is Misleading as Users Can Also Add Brands | D51: Admin | E51: User Management | F51: Unspec | G51: Low | H51: Backlog | I51: Md Mashiul Azam Chowdhury Efti | J51: Taslima Akbar Keya | K51: 5/12/2026 | L51: 5/12/2026
A52: CS-1397 | C52: User Managemnet | Brand Assignment Modal Flow is Confusing for Reassigning Brands | D52: Admin | E52: User Management | F52: Unspec | G52: Low | H52: Backlog | I52: Md Mashiul Azam Chowdhury Efti | J52: Taslima Akbar Keya | K52: 5/12/2026 | L52: 5/12/2026
A53: CS-1398 | C53: User Managemnet | No Role Removal Option Available in Assign Role Modal for Already Assigned Users | D53: Admin | E53: User Management | F53: Unspec | G53: Low | H53: Backlog | I53: Bijoy Chandra Nath | J53: Taslima Akbar Keya | K53: 5/12/2026 | L53: 5/12/2026
A54: CS-1399 | C54: User Managemnet | Incorrect Filter Columns Displayed in Invited Users Section | D54: Admin | E54: User Management | F54: Unspec | G54: Low | H54: Backlog | I54: Bijoy Chandra Nath | J54: Taslima Akbar Keya | K54: 5/12/2026 | L54: 5/12/2026
A55: ▸ Admin (General) (20)
A56: CS-1038 | B56: Bug | C56: [BE] Template files dont show required/mandatory fields | D56: Admin | E56: Admin (General) | F56: BE | G56: High | H56: Backlog | I56: Bijoy Chandra Nath | J56: Fariha Jabin | K56: 7/1/2025 | L56: 11/10/2025 | M56: Q1
A57: CS-1368 | C57: Admin | Caboodle Admin needs to access all Environments w/o the need for their login credentials | D57: Admin | E57: Admin (General) | F57: Unspec | G57: High | H57: Backlog | I57: Md Mashiul Azam Chowdhury Efti | J57: Constance Wolfe | K57: 5/2/2026 | L57: 5/2/2026
A58: CS-675 | B58: Sub-task | C58: Empowering Brand owner's edit in Banner SKU section | D58: Admin | E58: Admin (General) | F58: Unspec | G58: High | H58: Backlog | I58: Bijoy Chandra Nath | J58: Md Mashiul Azam Chowdhury | K58: 12/26/2024 | L58: 9/25/2025 | M58: ??
A59: CS-1039 | B59: Bug | C59: [BE] Field mismatch between manual form and upload template | D59: Admin | E59: Admin (General) | F59: BE | G59: Medium | H59: Backlog | I59: Bijoy Chandra Nath | J59: Fariha Jabin | K59: 7/1/2025 | L59: 11/10/2025 | M59: Fixed?
A60: CS-1356 | C60: [Admin] If current Session is over then User should automatically be logged out | D60: Admin | E60: Admin (General) | F60: Unspec | G60: Medium | H60: In Progress | I60: Md Mashiul Azam Chowdhury Efti | J60: Md Mashiul Azam Chowdhury Efti | K60: 4/27/2026 | L60: 5/5/2026
A61: CS-146 | B61: Task | C61: [BE] Module on off | D61: Admin | E61: Admin (General) | F61: BE | G61: Medium | H61: Backlog | I61: Bijoy Chandra Nath | J61: Md Mashiul Azam Chowdhury | K61: 12/3/2023 | L61: 12/3/2023 | M61: Discuss
A62: CS-147 | B62: Task | C62: [FE] Module on off | D62: Admin | E62: Admin (General) | F62: FE | G62: Medium | H62: Backlog | I62: Md Mashiul Azam Chowdhury | J62: Md Mashiul Azam Chowdhury | K62: 12/3/2023 | L62: 4/27/2025 | M62: Discuss
A63: CS-1035 | B63: Epic | C63: Admin bug tickets | D63: Admin | E63: Admin (General) | F63: Unspec | G63: Low | H63: Backlog | J63: Fariha Jabin | K63: 7/1/2025 | L63: 7/14/2025
A64: CS-1045 | B64: Bug | C64: brand name should be unique | D64: Admin | E64: Admin (General) | F64: Unspec | G64: Low | H64: Backlog | J64: Fariha Jabin | K64: 7/2/2025 | L64: 11/10/2025 | M64: Fixed?
A65: CS-1046 | B65: Bug | C65: brand description not fully visible if too long | D65: Admin | E65: Admin (General) | F65: Unspec | G65: Low | H65: Backlog | J65: Fariha Jabin | K65: 7/2/2025 | L65: 11/10/2025 | M65: Fixed?
A66: CS-1047 | B66: Bug | C66: blank file upload shows unclear error | D66: Admin | E66: Admin (General) | F66: Unspec | G66: Low | H66: Backlog | J66: Fariha Jabin | K66: 7/2/2025 | L66: 11/10/2025 | M66: Fixed?
A67: CS-1048 | B67: Bug | C67: brand upload template includes extra column | D67: Admin | E67: Admin (General) | F67: Unspec | G67: Low | H67: Backlog | J67: Fariha Jabin | K67: 7/2/2025 | L67: 11/10/2025 | M67: Q1
A68: CS-1049 | B68: Bug | C68: brand owner  email search filter not working | D68: Admin | E68: Admin (General) | F68: Unspec | G68: Low | H68: Backlog | J68: Fariha Jabin | K68: 7/2/2025 | L68: 11/10/2025 | M68: Q2
A69: CS-1050 | B69: Bug | C69: brand  export is not working | D69: Admin | E69: Admin (General) | F69: Unspec | G69: Low | H69: Backlog | J69: Fariha Jabin | K69: 7/2/2025 | L69: 11/10/2025 | M69: Q2
A70: CS-1062 | B70: Bug | C70: banner profile page: if name field empty, try to save, cant save, no error message shown | D70: Admin | E70: Admin (General) | F70: Unspec | G70: Low | H70: Backlog | J70: Fariha Jabin | K70: 7/9/2025 | L70: 11/10/2025 | M70: Fixed?
A71: CS-1063 | B71: Bug | C71: banner profile page: change password is not working | D71: Admin | E71: Admin (General) | F71: Unspec | G71: Low | H71: Backlog | J71: Fariha Jabin | K71: 7/9/2025 | L71: 11/10/2025 | M71: Fixed?
A72: CS-1064 | B72: Bug | C72: login: if password is less than 6 characters, sign-up fails with no error message | D72: Admin | E72: Admin (General) | F72: Unspec | G72: Low | H72: Backlog | J72: Fariha Jabin | K72: 7/9/2025 | L72: 11/10/2025 | M72: Q1
A73: CS-245 | B73: Task | C73: [BE] Admin - Activity Log | D73: Admin | E73: Admin (General) | F73: BE | G73: Low | H73: Backlog | I73: Bijoy Chandra Nath | J73: Md Mashiul Azam Chowdhury | K73: 12/21/2023 | L73: 12/21/2023 | M73: Discuss
A74: CS-246 | B74: Task | C74: [FE] Admin - Activity Log | D74: Admin | E74: Admin (General) | F74: FE | G74: Low | H74: Backlog | I74: Md Mashiul Azam Chowdhury | J74: Md Mashiul Azam Chowdhury | K74: 12/21/2023 | L74: 4/27/2025 | M74: Discuss
A75: CS-247 | B75: Task | C75: [BE] Admin - Upload Effeciency | D75: Admin | E75: Admin (General) | F75: BE | G75: Low | H75: Backlog | I75: Bijoy Chandra Nath | J75: Md Mashiul Azam Chowdhury | K75: 12/21/2023 | L75: 12/21/2023 | M75: Discuss
A76: CS-1201 | B76: Task | C76: Fix filter so User only see the Retailers they manage, the TSS & BAP Promotions they create and the Promotions on the Calendar | D76: Brand | E76: Trade Spend Sandbox | F76: Unspec | G76: Medium | H76: Backlog | I76: Md Mashiul Azam Chowdhury | J76: Constance Wolfe | K76: 10/27/2025 | L76: 11/10/2025 | M76: Moved from Brand
A77: CS-1429 | B77: Sub-task | C77: [FE] Admin Sent Emails screen with resend & bulk resend | D77: Admin | E77: Admin | G77: High | H77: Backlog | I77: Md Mashiul Azam Chowdhury Efti | J77: Md Mashiul Azam Chowdhury Efti | K77: 46204.713 | L77: 46204.714
A78: CS-1427 | B78: Story | C78: Admin - View sent email log with resend and bulk resend | D78: Admin | E78: Admin | G78: High | H78: In Progress | I78: Kazi Towfiq Tasmin Ornov | J78: Md Mashiul Azam Chowdhury Efti | K78: 46204.71 | L78: 46205.465
A79: CS-1432 | B79: Task | C79: User-Managemet: Replace Role-Specific Invite Email Templates with a Shared Template | D79: Admin | E79: Admin | G79: Medium | H79: In Progress | I79: Kazi Towfiq Tasmin Ornov | J79: Md Mashiul Azam Chowdhury Efti | K79: 46210.514 | L79: 46210.515
A80: CS-1430 | B80: Story | C80: Setup & Develop SNS Webhook to Receive Email Sending Events | D80: Admin | E80: Admin | G80: High | H80: In Progress | I80: Kazi Towfiq Tasmin Ornov | J80: Md Mashiul Azam Chowdhury Efti | K80: 46208.614 | L80: 46209.378
A81: CS-1428 | B81: Sub-task | C81: [BE] Email log API with single & bulk resend | D81: Admin | E81: Admin | G81: High | H81: In Progress | I81: Kazi Towfiq Tasmin Ornov | J81: Md Mashiul Azam Chowdhury Efti | K81: 46204.711 | L81: 46205.465
A82: Need
C84: CRM DATA UPLOAD
B85: ACDU1 | C85: Perform Filter Audit in all CRM Data Upload > User should be able to filter by any column
C86: DASHBOARD
B87: AD1 | C87: Prototype with Flags alerting user of upcoming Task, promotional submission, category Review Deadlines
C88: ADMIN CONTROLS
B89: AAC1 | C89: Admin should be able to control the Icons on the buttons 0n the Reports Page (Example Monthly Report)
B90: AAC2 | C90: Control Dropdown options for Broker Category Review Brand Report
C91: NEED A WAY TO:
B92: ANAWT1 | C92: Single Trade Spend for Basic Subscription
C93: STORE REPORT
B94: ASR1 | C94: Need to eliminate/merge store duplicates

Sheet Platform & Cross-Cutting
A1: Platform & Cross-Cutting — 28 tickets
A3: Issue Key | B3: Type | C3: Summary | D3: Area | E3: Caboodle Module | F3: FE/BE | G3: Priority | H3: Status | I3: Assignee | J3: Reporter | K3: Created | L3: Updated | M3: Due / Note
A4: ▸ Infrastructure / Cross-Cutting (28)
A5: CS-1239 | B5: Task | C5: [BE] Forecast related endpoint implementation (Export) | D5: Platform & Cross-Cutting | E5: Infrastructure / Cross-Cutting | F5: BE | G5: Highest | H5: In Progress | I5: Bijoy Chandra Nath | J5: Bijoy Chandra Nath | K5: 12/11/2025 | L5: 12/11/2025 | M5: Provide Update
A6: CS-570 | B6: Task | C6: Filters Updates | D6: Platform & Cross-Cutting | E6: Infrastructure / Cross-Cutting | F6: Unspec | G6: Highest | H6: Reopened | I6: Md Mashiul Azam Chowdhury | J6: Heather Whittier | K6: 7/9/2024 | L6: 4/27/2025
A7: CS-1163 | B7: Task | C7: Background job for All Export | D7: Platform & Cross-Cutting | E7: Infrastructure / Cross-Cutting | F7: Unspec | G7: High | H7: In Progress | I7: Bijoy Chandra Nath | J7: Md Mashiul Azam Chowdhury | K7: 9/10/2025 | L7: 11/6/2025 | M7: Provide update
A8: CS-1164 | B8: Task | C8: [FE] 30 MB max size message for import | D8: Platform & Cross-Cutting | E8: Infrastructure / Cross-Cutting | F8: FE | G8: High | H8: Backlog | I8: Md Mashiul Azam Chowdhury | J8: Md Mashiul Azam Chowdhury | K8: 9/10/2025 | L8: 11/6/2025 | M8: Q1
A9: CS-1213 | B9: Task | C9: Resolve all email service reliability issues | D9: Platform & Cross-Cutting | E9: Infrastructure / Cross-Cutting | F9: Unspec | G9: High | H9: Backlog | I9: Bijoy Chandra Nath | J9: Md Mashiul Azam Chowdhury | K9: 11/6/2025 | L9: 11/24/2025 | M9: Complete?
A10: CS-1217 | B10: Task | C10: [BE] Implement the Upload/Download Wizard to handle imports/exports. | D10: Platform & Cross-Cutting | E10: Infrastructure / Cross-Cutting | F10: BE | G10: High | H10: Backlog | I10: Bijoy Chandra Nath | J10: Md Mashiul Azam Chowdhury | K10: 11/6/2025 | L10: 1/29/2026 | M10: Complete?
A11: CS-1218 | B11: Task | C11: Remove the 30MB upload restriction (target: 200MB+). | D11: Platform & Cross-Cutting | E11: Infrastructure / Cross-Cutting | F11: Unspec | G11: High | H11: Backlog | J11: Md Mashiul Azam Chowdhury | K11: 11/6/2025 | L11: 11/6/2025 | M11: Complete?
A12: CS-1220 | B12: Task | C12: Conduct end-to-end QA with real-world data samples. | D12: Platform & Cross-Cutting | E12: Infrastructure / Cross-Cutting | F12: QA | G12: High | H12: Backlog | J12: Md Mashiul Azam Chowdhury | K12: 11/6/2025 | L12: 11/6/2025 | M12: Q1
A13: CS-1221 | B13: Task | C13: Integrate Tableau Reporting into the platform. | D13: Platform & Cross-Cutting | E13: Infrastructure / Cross-Cutting | F13: Unspec | G13: High | H13: Backlog | J13: Md Mashiul Azam Chowdhury | K13: 11/6/2025 | L13: 11/6/2025 | M13: Not Doing
A14: CS-1224 | B14: Task | C14: Conduct year-end QA, finalize documentation, and prepare release packages. | D14: Platform & Cross-Cutting | E14: Infrastructure / Cross-Cutting | F14: QA | G14: High | H14: Backlog | J14: Md Mashiul Azam Chowdhury | K14: 11/6/2025 | L14: 11/6/2025 | M14: Q1
A15: CS-1288 | C15: Ask Caboodle | Coordinate with ML/AI engineer > Implement Character Requirements for Billing | D15: Platform & Cross-Cutting | E15: Infrastructure / Cross-Cutting | F15: Unspec | G15: High | H15: Backlog | I15: Md Mashiul Azam Chowdhury Efti | J15: Constance Wolfe | K15: 3/31/2026 | L15: 3/31/2026
A16: CS-1341 | C16: Margin Calculator | POP Out Calculator | D16: Platform & Cross-Cutting | E16: Infrastructure / Cross-Cutting | F16: Unspec | G16: High | H16: Backlog | I16: Bijoy Chandra Nath | J16: Constance Wolfe | K16: 4/9/2026 | L16: 5/4/2026
A17: CS-1362 | C17: Broker Dashboard | Ask Caboodle | D17: Platform & Cross-Cutting | E17: Infrastructure / Cross-Cutting | F17: Unspec | G17: High | H17: Backlog | I17: Md Mashiul Azam Chowdhury Efti | J17: Constance Wolfe | K17: 4/29/2026 | L17: 4/29/2026
A18: CS-514 | B18: Task | C18: Optimize the tables to ensure that the site remains unaffected even with a large amount of data. | D18: Platform & Cross-Cutting | E18: Infrastructure / Cross-Cutting | F18: Unspec | G18: High | H18: Backlog | I18: Md Mashiul Azam Chowdhury | J18: Md Mashiul Azam Chowdhury | K18: 5/7/2024 | L18: 5/7/2024 | M18: Complete?
A19: CS-517 | B19: Task | C19: Apply Indexing Mechanism in Database | D19: Platform & Cross-Cutting | E19: Infrastructure / Cross-Cutting | F19: Unspec | G19: High | H19: In Progress | I19: Bijoy Chandra Nath | J19: Bijoy Chandra Nath | K19: 5/7/2024 | L19: 9/25/2025 | M19: Provide update
A20: CS-955 | B20: Epic | C20: UX Audit | D20: Platform & Cross-Cutting | E20: Infrastructure / Cross-Cutting | F20: Unspec | G20: High | H20: Backlog | I20: Abdullah Al Mahmud | J20: Md Mashiul Azam Chowdhury | K20: 5/15/2025 | L20: 11/6/2025 | M20: ??
A21: CS-1166 | B21: Task | C21: [BE] Check email delivery status for new Sign up | D21: Platform & Cross-Cutting | E21: Infrastructure / Cross-Cutting | F21: BE | G21: Medium | H21: Backlog | I21: Bijoy Chandra Nath | J21: Md Mashiul Azam Chowdhury | K21: 9/10/2025 | L21: 11/6/2025 | M21: Complete?
A22: CS-190 | B22: Task | C22: Caboodle Phase 2 Requirements | D22: Platform & Cross-Cutting | E22: Infrastructure / Cross-Cutting | F22: Unspec | G22: Medium | H22: Backlog | J22: Md Mashiul Azam Chowdhury | K22: 12/9/2023 | L22: 2/5/2024
A23: CS-405 | B23: Task | C23: Monitoring Service | D23: Platform & Cross-Cutting | E23: Infrastructure / Cross-Cutting | F23: Unspec | G23: Medium | H23: Backlog | I23: Bijoy Chandra Nath | J23: Bijoy Chandra Nath | K23: 2/29/2024 | L23: 9/25/2025 | M23: ??
A24: CS-512 | B24: Task | C24: Check if we can further utilize caching from any other areas | D24: Platform & Cross-Cutting | E24: Infrastructure / Cross-Cutting | F24: Unspec | G24: Medium | H24: Backlog | I24: Md Mashiul Azam Chowdhury | J24: Md Mashiul Azam Chowdhury | K24: 5/7/2024 | L24: 5/7/2024 | M24: ??
A25: CS-518 | B25: Task | C25: Automatically Remove Deleted Records After Certain Period Of Time | D25: Platform & Cross-Cutting | E25: Infrastructure / Cross-Cutting | F25: Unspec | G25: Medium | H25: Backlog | I25: Bijoy Chandra Nath | J25: Bijoy Chandra Nath | K25: 5/7/2024 | L25: 9/25/2025 | M25: ??
A26: CS-519 | B26: Task | C26: [BE] Re-Structuring The Code Base | D26: Platform & Cross-Cutting | E26: Infrastructure / Cross-Cutting | F26: BE | G26: Medium | H26: In Progress | I26: Bijoy Chandra Nath | J26: Bijoy Chandra Nath | K26: 5/7/2024 | L26: 9/25/2025 | M26: Provide update
A27: CS-1036 | B27: Bug | C27: newly created items not appearing without refresh | D27: Platform & Cross-Cutting | E27: Infrastructure / Cross-Cutting | F27: Unspec | G27: Low | H27: Ready for Production | I27: Md Mashiul Azam Chowdhury | J27: Fariha Jabin | K27: 7/1/2025 | L27: 11/18/2025 | M27: Provide update
A28: CS-1040 | B28: Bug | C28: ui issue  button corners broken | D28: Platform & Cross-Cutting | E28: Infrastructure / Cross-Cutting | F28: Unspec | G28: Low | H28: Backlog | I28: Md Mashiul Azam Chowdhury | J28: Fariha Jabin | K28: 7/1/2025 | L28: 11/10/2025 | M28: Fixed?
A29: CS-1406 | C29: Switching from Broker Dashboard to Brand Dashboard Sometimes Does Not Work | D29: Platform & Cross-Cutting | E29: Infrastructure / Cross-Cutting | F29: Unspec | G29: Low | H29: Backlog | I29: Md Mashiul Azam Chowdhury Efti | J29: Fariha Jabin | K29: 5/18/2026 | L29: 5/18/2026
A30: CS-701 | B30: Story | C30: Share link of pages like in google and restrict it to view only | D30: Platform & Cross-Cutting | E30: Infrastructure / Cross-Cutting | F30: Unspec | G30: Low | H30: Backlog | I30: Constance Wolfe | J30: Md Mashiul Azam Chowdhury | K30: 2/17/2025 | L30: 11/6/2025 | M30: ??
A31: CS-894 | B31: Epic | C31: Issues from QA audit | D31: Platform & Cross-Cutting | E31: Infrastructure / Cross-Cutting | F31: QA | G31: Low | H31: Backlog | J31: Fariha Jabin | K31: 5/5/2025 | L31: 11/6/2025 | M31: ??
A32: CS-973 | B32: Story | C32: Regression Test | D32: Platform & Cross-Cutting | E32: Infrastructure / Cross-Cutting | F32: QA | G32: Low | H32: Backlog | J32: Fariha Jabin | K32: 5/26/2025 | L32: 5/29/2025 | M32: ??
A33: Need
C35: ENHANCEMENTS NEEDED TO SCALE TO THOUSANDS OF USERS
C36: Caching
C37: Big Data Management
C38: New Brand Onbording Process Effencencies
